{
"meta":{"test_sets":[],"test_metrics":[],"learn_metrics":[{"best_value":"Min","name":"RMSE"}],"launch_mode":"Train","parameters":"","iteration_count":1000,"learn_sets":["learn"],"name":"experiment"},
"iterations":[
{"learn":[0.1490275053],"iteration":0,"passed_time":0.160988147,"remaining_time":160.8271589},
{"learn":[0.1452499051],"iteration":1,"passed_time":0.1779074568,"remaining_time":88.77582095},
{"learn":[0.1414760477],"iteration":2,"passed_time":0.199123914,"remaining_time":66.17551407},
{"learn":[0.1377290269],"iteration":3,"passed_time":0.2157336573,"remaining_time":53.71768066},
{"learn":[0.1343880094],"iteration":4,"passed_time":0.2259386564,"remaining_time":44.96179263},
{"learn":[0.1310000039],"iteration":5,"passed_time":0.2359674853,"remaining_time":39.09194673},
{"learn":[0.1279967311],"iteration":6,"passed_time":0.2532295159,"remaining_time":35.92241561},
{"learn":[0.1251727784],"iteration":7,"passed_time":0.2660441285,"remaining_time":32.98947193},,
{"learn":[0.1213263335],"iteration":8,"passed_time":0.2866031105,"remaining_time":31.5581869,
,
{"learn":[0.1184886117],"iteration":9,"passed_time":0.307674023,"remaining_time":30.45972828},
{"learn":[0.1159989574],"iteration":10,"passed_time":0.3431235962,"remaining_time":30.8499306},
{"learn":[0.1135313918],"iteration":11,"passed_time":0.3546426343,"remaining_time":29.19891023},
{"learn":[0.1112191136],"iteration":12,"passed_time":0.3709575752,"remaining_time":28.16424051},
{"learn":[0.1089763995],"iteration":13,"passed_time":0.393896938,"remaining_time":27.74159863},
{"learn":[0.1068890341],"iteration":14,"passed_time":0.4025281597,"remaining_time":26.43268249},
{"learn":[0.104736576],"iteration":15,"passed_time":0.4272598731,"remaining_time":26.2764822},
{"learn":[0.102717023],"iteration":16,"passed_time":0.439720077,"remaining_time":25.4261668},
{"learn":[0.1007439125],"iteration":17,"passed_time":0.4589738579,"remaining_time":25.0395738,
{"learn":[0.09909927437],"iteration":18,"passed_time":0.4728183164,"remaining_time":24.41235623},
{"learn":[0.09721721801],"iteration":19,"passed_time":0.4927197877,"remaining_time":24.1432696},,
{"learn":[0.09525886434],"iteration":20,"passed_time":0.5039932072,"remaining_time":23.49568333,,
{"learn":[0.09358577403],"iteration":21,"passed_time":0.5309522235,"remaining_time":23.6032397,
{"learn":[0.09172506258],"iteration":22,"passed_time":0.5477736199,"remaining_time":23.26847072},
{"learn":[0.09014509412],"iteration":23,"passed_time":0.5824954271,"remaining_time":23.68814737},
,
{"learn":[0.08890045662],"iteration":24,"passed_time":0.5932013615,"remaining_time":23.1348531,,
{"learn":[0.08741968682],"iteration":25,"passed_time":0.6203516895,"remaining_time":23.23932868,
{"learn":[0.08579116844],"iteration":26,"passed_time":0.6463731439,"remaining_time":23.29337293},
{"learn":[0.08436622887],"iteration":27,"passed_time":0.6582673497,"remaining_time":22.85128085},,
{"learn":[0.08329701756],"iteration":28,"passed_time":0.6823594633,"remaining_time":22.8472772,,
{"learn":[0.08205285096],"iteration":29,"passed_time":0.7025629885,"remaining_time":22.7162033},
{"learn":[0.08083190202],"iteration":30,"passed_time":0.7320866634,"remaining_time":22.88361216},
{"learn":[0.07955475863],"iteration":31,"passed_time":0.7415186249,"remaining_time":22.4309384},
{"learn":[0.07845172166],"iteration":32,"passed_time":0.7787287507,"remaining_time":22.81911218},
{"learn":[0.07724732109],"iteration":33,"passed_time":0.7830345288,"remaining_time":22.24739279},,
{"learn":[0.07614648443],"iteration":34,"passed_time":0.7870414036,"remaining_time":21.69985584,,
{"learn":[0.07512166998],"iteration":35,"passed_time":0.8123406485,"remaining_time":21.75267736},
{"learn":[0.07409841995],"iteration":36,"passed_time":0.8306524499,"remaining_time":21.61941376},
{"learn":[0.07307620892],"iteration":37,"passed_time":0.8432946227,"remaining_time":21.34866913},
{"learn":[0.07220351111],"iteration":38,"passed_time":0.8908552262,"remaining_time":21.95158647},
{"learn":[0.07148001128],"iteration":39,"passed_time":0.9090004883,"remaining_time":21.81601172},
{"learn":[0.07072009472],"iteration":40,"passed_time":0.9127904669,"remaining_time":21.35039165},
{"learn":[0.06985103444],"iteration":41,"passed_time":0.927642375,"remaining_time":21.15908084},
{"learn":[0.06897920754],"iteration":42,"passed_time":0.9347042329,"remaining_time":20.80260351},
{"learn":[0.06816175571],"iteration":43,"passed_time":0.9509187679,"remaining_time":20.66087141},
{"learn":[0.06735771999],"iteration":44,"passed_time":0.9610926964,"remaining_time":20.39652278},
{"learn":[0.06663057947],"iteration":45,"passed_time":0.976235237,"remaining_time":20.24626991},
{"learn":[0.06591379525],"iteration":46,"passed_time":0.982412231,"remaining_time":19.91997566},
{"learn":[0.06515503464],"iteration":47,"passed_time":0.9942261902,"remaining_time":19.71881944},
{"learn":[0.06445595917],"iteration":48,"passed_time":0.9994980373,"remaining_time":19.39842109},
{"learn":[0.06382344183],"iteration":49,"passed_time":1.004609268,"remaining_time":19.08757609},
{"learn":[0.0632759309],"iteration":50,"passed_time":1.010075478,"remaining_time":18.79532606},
{"learn":[0.06261726649],"iteration":51,"passed_time":1.017821575,"remaining_time":18.55567025},
{"learn":[0.06202238653],"iteration":52,"passed_time":1.024863363,"remaining_time":18.31218123},
{"learn":[0.06148406487],"iteration":53,"passed_time":1.033279972,"remaining_time":18.10153432},
{"learn":[0.06094175987],"iteration":54,"passed_time":1.040384265,"remaining_time":17.87569328},
{"learn":[0.06033845435],"iteration":55,"passed_time":1.052353721,"remaining_time":17.73967701},
{"learn":[0.05994730591],"iteration":56,"passed_time":1.059125647,"remaining_time":17.52202606},
{"learn":[0.05945949572],"iteration":57,"passed_time":1.076776205,"remaining_time":17.48833078},
{"learn":[0.05904145966],"iteration":58,"passed_time":1.085047421,"remaining_time":17.3055868,
{"learn":[0.05978819611],"iteration":59,"passed_time":1.117006385,"remaining_time":17.4997667},
{,
{"learn":[0.05803609385],"iteration":60,"passed_time":1.105037431,"remaining_time":17.010330,
{"learn":[0.05892710653],"iteration":61,"passed_time":1.145146953,"remaining_time":17.32496519},
{,
{"learn":[0.05724593894],"iteration":62,"passed_time":1.128794135,"remaining_time":16.78857,
{",
{"learn":[0.05689966301],"iteration":63,"passed_time":1.151086872,"remaining_time":16.8346455},
{"learn":[0.05656694956],"iteration":64,"passed_time":1.160635282,"remaining_time":16.69529213},
{"learn":[0.05622824256],"iteration":65,"passed_time":1.16950324,"remaining_time":16.55024282},
{"learn":[0.05590004804],"iteration":66,"passed_time":1.177007004,"remaining_time":16.3902617,
,
{"learn":[0.05559363061],"iteration":67,"passed_time":1.185242307,"remaining_time":16.2447916,
{"learn":[0.0564035208],"iteration":68,"passed_time":1.221550286,"remaining_time":16.48207705},
{"learn":[0.0560884804],"iteration":69,"passed_time":1.229623397,"remaining_time":16.33642514},
{"learn":[0.05582316503],"iteration":70,"passed_time":1.251175613,"remaining_time":16.37101612},
{"learn":[0.0554902571],"iteration":71,"passed_time":1.259288309,"remaining_time":16.2308271},
{"learn":[0.05518561423],"iteration":72,"passed_time":1.272608092,"remaining_time":16.16037948},
{"learn":[0.05491015279],"iteration":73,"passed_time":1.285133023,"remaining_time":16.08152946},
{"learn":[0.05462267962],"iteration":74,"passed_time":1.295779532,"remaining_time":15.98128089},
{"learn":[0.0543884082],"iteration":75,"passed_time":1.306307064,"remaining_time":15.88194378},
{"learn":[0.05414602282],"iteration":76,"passed_time":1.316552403,"remaining_time":15.78153075},
{"learn":[0.05385889169],"iteration":77,"passed_time":1.323736242,"remaining_time":15.64724122},
{"learn":[0.05364377482],"iteration":78,"passed_time":1.332831008,"remaining_time":15.53844758},
{"learn":[0.0534397265],"iteration":79,"passed_time":1.339213729,"remaining_time":15.40095789},
{"learn":[0.05313508286],"iteration":80,"passed_time":1.34794224,"remaining_time":15.29331999},
{"learn":[0.05292016469],"iteration":81,"passed_time":1.355578183,"remaining_time":15.17586307},
{"learn":[0.05271727741],"iteration":82,"passed_time":1.36624876,"remaining_time":15.09457967},
{"learn":[0.05248528285],"iteration":83,"passed_time":1.373075773,"remaining_time":14.97306439},
{"l,
{"learn":[0.05137145937],"iteration":84,"passed_time":1.357769879,"remaining_time":14.615,
{"le,
{"learn":[0.05113954853],"iteration":85,"passed_time":1.368718799,"remaining_time":14.546,
{"le,
{"learn":[0.05094137243],"iteration":86,"passed_time":1.388091671,"remaining_time":14.56698501},
{"learn":[0.05073014575],"iteration":87,"passed_time":1.397252579,"remaining_time":14.48061763},
{"learn":[0.05058320585],"iteration":88,"passed_time":1.406415567,"remaining_time":14.,
{"learn,
{"learn":[0.05041016302],"iteration":89,"passed_time":1.416723934,"remaining_time":14.,
{"learn,
{"learn":[0.05022464178],"iteration":90,"passed_time":1.43099346,"remaining_time":14.29420939},
{"learn":[0.0500629061],"iteration":91,"passed_time":1.443899171,"remaining_time":14.25065703},
{"learn":[0.04983788956],"iteration":92,"passed_time":1.456157711,"remaining_time":14.20145208},
{"learn":[0.04969621266],"iteration":93,"passed_time":1.464923147,"remaining_time":14.11936565},
{"learn":[0.04959240648],"iteration":94,"passed_time":1.481654513,"remaining_time":14.11470878},
{"learn":[0.04945744958],"iteration":95,"passed_time":1.496942927,"remaining_time":14.09621257},
{"learn":[0.04927654916],"iteration":96,"passed_time":1.5005328,"remaining_time":13.96887751},
{"learn":[0.04909251996],"iteration":97,"passed_time":1.509178573,"remaining_time":13.89060278},
{"learn":[0.04892001772],"iteration":98,"passed_time":1.519476089,"remaining_time":13.82876724},
{"learn":[0.04877816817],"iteration":99,"passed_time":1.522913058,"remaining_time":13.70621752},
{"learn":[0.04865154238],"iteration":100,"passed_time":1.536035414,"remaining_time":13.67223601},
{"learn":[0.04852679464],"iteration":101,"passed_time":1.542470639,"remaining_time":13.57979053},
{"learn":[0.04840132437],"iteration":102,"passed_time":1.558642924,"remaining_time":13.57381265},
{"learn":[0.04820713665],"iteration":103,"passed_time":1.563846591,"remaining_time":13.47313986},
{"learn":[0.0480574844],"iteration":104,"passed_time":1.569997619,"remaining_time":13.38236065},
{"learn":[0.04789576258],"iteration":105,"passed_time":1.582090487,"remaining_time":13.34329147},
{"learn":[0.04775860292],"iteration":106,"passed_time":1.594205658,"remaining_time":13.30491264},
{"learn":[0.04764795803],"iteration":107,"passed_time":1.60224298,"remaining_time":13.23334017},
{"learn":[0.04751394082],"iteration":108,"passed_time":1.607967463,"remaining_time":13.14402761},
{"learn":[0.0473798301],"iteration":109,"passed_time":1.620844833,"remaining_time":13.11410819},
{"learn":[0.04727666156],"iteration":110,"passed_time":1.630110509,"remaining_time":13.05556975},
{"learn":[0.04715678799],"iteration":111,"passed_time":1.639464024,"remaining_time":12.99860762},
{"learn":[0.04701744778],"iteration":112,"passed_time":1.649086919,"remaining_time":12.94460263},
{"learn":[0.04688993864],"iteration":113,"passed_time":1.661048286,"remaining_time":12.90955071},
{"learn":[0.04678853313],"iteration":114,"passed_time":1.671614923,"remaining_time":12.86416702},
{"learn":[0.04665833639],"iteration":115,"passed_time":1.681755159,"remaining_time":12.81613414},
{"learn":[0.04655309585],"iteration":116,"passed_time":1.691156398,"remaining_time":12.76317179},
{"learn":[0.04644753895],"iteration":117,"passed_time":1.701806384,"remaining_time":12.72028161},
{"learn":[0.0463894165],"iteration":118,"passed_time":1.718190701,"remaining_time":12.72038662},
{"learn":[0.04625568317],"iteration":119,"passed_time":1.733277264,"remaining_time":12.71069993},
{"learn":[0.0461615364],"iteration":120,"passed_time":1.74014533,"remaining_time":12.64122104},
{"learn":[0.04604457281],"iteration":121,"passed_time":1.751496566,"remaining_time":12.60503266},
{"learn":[0.04600187966],"iteration":122,"passed_time":1.756825789,"remaining_time":12.52631071},
{"learn":[0.04592264612],"iteration":123,"passed_time":1.762271475,"remaining_time":12.44959526},
{"learn":[0.04583168436],"iteration":124,"passed_time":1.769740468,"remaining_time":12.38818328},
{"learn":[0.04572676167],"iteration":125,"passed_time":1.778658192,"remaining_time":12.33767666},
{"learn":[0.04569718832],"iteration":126,"passed_time":1.786406885,"remaining_time":12.27978906},
{"learn":[0.04561538356],"iteration":127,"passed_time":1.798412841,"remaining_time":12.25168748},
{"learn":[0.0455523855],"iteration":128,"passed_time":1.814152275,"remaining_time":12.24904365},
{"learn":[0.04548628683],"iteration":129,"passed_time":1.822459213,"remaining_time":12.19645781},
{"learn":[0.04539207154],"iteration":130,"passed_time":1.831867674,"remaining_time":12.15185503},
{"learn":[0.04534446457],"iteration":131,"passed_time":1.838398887,"remaining_time":12.08886541},
{"learn":[0.04523206697],"iteration":132,"passed_time":1.857977943,"remaining_time":12.11178103},
{"learn":[0.04514969454],"iteration":133,"passed_time":1.86309306,"remaining_time":12.04058649},
{"learn":[0.04501206386],"iteration":134,"passed_time":1.870985996,"remaining_time":11.98816953},
{"learn":[0.0449611858],"iteration":135,"passed_time":1.884476537,"remaining_time":11.97196859},
{"learn":[0.04485256669],"iteration":136,"passed_time":1.895213065,"remaining_time":11.93845894},
{"learn":[0.04480748599],"iteration":137,"passed_time":1.903145424,"remaining_time":11.88776345},
{"learn":[0.04473761947],"iteration":138,"passed_time":1.917344315,"remaining_time":11.87649968},
{"learn":[0.04467406924],"iteration":139,"passed_time":1.925914592,"remaining_time":11.83061821},
{"learn":[0.04459794529],"iteration":140,"passed_time":1.932785345,"remaining_time":11.77491214},
{"learn":[0.04449435962],"iteration":141,"passed_time":1.941386894,"remaining_time":1,
{"learn":,
{"learn":[0.04445690088],"iteration":142,"passed_time":1.95867472,"remaining_time":11.7383513},
{"learn":[0.04437432925],"iteration":143,"passed_time":1.97343072,"remaining_time":11.73094928},
{"learn":[0.04431367833],"iteration":144,"passed_time":1.988274833,"remaining_time":11.72396539},
{"learn":[0.04422872935],"iteration":145,"passed_time":2.002022861,"remaining_time":11.71046249},
{"learn":[0.04414208882],"iteration":146,"passed_time":2.016887898,"remaining_time":11.70343794},
{"learn":[0.04405481962],"iteration":147,"passed_time":2.028532421,"remaining_time":11.67776772},
{"learn":[0.04399194781],"iteration":148,"passed_time":2.039490376,"remaining_time":11,
{"learn":[0.04488295647],"iteration":149,"passed_time":2.082734159,"remaining_time":11.80216023},
{"learn":[0.04482176689],"iteration":150,"passed_time":2.089042421,"remaining_time":11.7456756},
{"learn":[0.04474302057],"iteration":151,"passed_time":2.101916756,"remaining_time":11.72648295},
{"learn":[0.04469157322],"iteration":152,"passed_time":2.110541275,"remaining_time":11.68384614},
{"learn":[0.04465159214],"iteration":153,"passed_time":2.137991551,"remaining_time":11.74507047},
{"learn":[0.04458232211],"iteration":154,"passed_time":2.151023318,"remaining_time":11.72654647},
{"learn":[0.04452581858],"iteration":155,"passed_time":2.174877429,"remaining_time":11.76664455},
{"learn":[0.04447444362],"iteration":156,"passed_time":2.187273941,"remaining_time":11.74440721},
{"learn":[0.04442763455],"iteration":157,"passed_time":2.201190893,"remaining_time":11.73039704},
{"learn":[0.04437301674],"iteration":158,"passed_time":2.213295073,"remaining_time":11.70679973},
{"learn":[0.04428205478],"iteration":159,"passed_time":2.220110164,"remaining_time":11.65557836},
{"learn":[0.04423026832],"iteration":160,"passed_time":2.228444607,"remaining_time":11.61282624},
{"learn":[0.04415590193],"iteration":161,"passed_time":2.247462854,"remaining_time":11.62576464},
{"learn":[0.0441302823],"iteration":162,"passed_time":2.255989636,"remaining_time":11.58443758},
{"learn":[0.04407150578],"iteration":163,"passed_time":2.263866609,"remaining_time":11.54019808},
{"learn":[0.04399548682],"iteration":164,"passed_time":2.277173569,"remaining_time":11.52387837},
{"learn":[0.04390573383],"iteration":165,"passed_time":2.297848762,"remaining_time":11.54461366},
{"learn":[0.04380525566],"iteration":166,"passed_time":2.314364517,"remaining_time":11.54410564},
{"learn":[0.04377390525],"iteration":167,"passed_time":2.322805835,"remaining_time":11.50341937},
{"learn":[0.04371622106],"iteration":168,"passed_time":2.334440529,"remaining_time":11.47881704},
{"learn":[0.04366034221],"iteration":169,"passed_time":2.345369182,"remaining_time":11.45092012},
{"learn":[0.04360329184],"iteration":170,"passed_time":2.357855731,"remaining_time":11.43077427},
{"learn":[0.04352922705],"iteration":171,"passed_time":2.363946363,"remaining_time":11.37992784},
{"learn":[0.04350550851],"iteration":172,"passed_time":2.387409717,"remaining_time":11.41264645},
{"learn":[0.04342057871],"iteration":173,"passed_time":2.397153817,"remaining_time":11.37959226},
{"learn":[0.04337797491],"iteration":174,"passed_time":2.410343465,"remaining_time":11.36304776},
{"learn":[0.04329561399],"iteration":175,"passed_time":2.425679824,"remaining_time":11.3565919},
{"learn":[0.04324128894],"iteration":176,"passed_time":2.43927197,"remaining_time":11.3419256},
{"learn":[0.04318229451],"iteration":177,"passed_time":2.448640373,"remaining_time":11.30776621},
{"learn":[0.04311846262],"iteration":178,"passed_time":2.460990727,"remaining_time":11.28756082},
{"learn":[0.04307383528],"iteration":179,"passed_time":2.483419622,"remaining_time":11.31335606},
{"learn":[0.04298863386],"iteration":180,"passed_time":2.498969738,"remaining_time":11.3074929},
{"learn":[0.04296887731],"iteration":181,"passed_time":2.509252866,"remaining_time":11.27785079},
{"learn":[0.04294944351],"iteration":182,"passed_time":2.519912963,"remaining_time":11.25010323},
{"learn":[0.04289732512],"iteration":183,"passed_time":2.530582596,"remaining_time":11.22258369},
{"learn":[0.0428093195],"iteration":184,"passed_time":2.540065322,"remaining_time":11.1900175},
{"learn":[0.04277493526],"iteration":185,"passed_time":2.548187915,"remaining_time":11.15174711},
{"learn":[0.04272386806],"iteration":186,"passed_time":2.555418492,"remaining_time":11.10992104},
{"learn":[0.04264562222],"iteration":187,"passed_time":2.579228332,"remaining_time":11.14007131},
{"learn":[0.04258854468],"iteration":188,"passed_time":2.593138081,"remaining_time":11.12716922},
{"learn":[0.04256991447],"iteration":189,"passed_time":2.604363986,"remaining_time":11.10281489},
{"learn":[0.04246851858],"iteration":190,"passed_time":2.620514589,"remaining_time":11.09945708},
{"learn":[0.04244582622],"iteration":191,"passed_time":2.632502868,"remaining_time":11.07844957},
{"learn":[0.04243080985],"iteration":192,"passed_time":2.64675386,"remaining_time":11.06699671},
{"learn":[0.04241396347],"iteration":193,"passed_time":2.661850661,"remaining_time":11.05902903},
{"learn":[0.04235389976],"iteration":194,"passed_time":2.677428296,"remaining_time":11.05297322},
{"learn":[0.04229545356],"iteration":195,"passed_time":2.686034109,"remaining_time":11.01822155},
{"learn":[0.04226048937],"iteration":196,"passed_time":2.693745887,"remaining_time":10.9800911},
{"learn":[0.04223886653],"iteration":197,"passed_time":2.704632685,"remaining_time":10.95512835},
{"learn":[0.04222290871],"iteration":198,"passed_time":2.713223099,"remaining_time":10.92106383},
{"learn":[0.04220827383],"iteration":199,"passed_time":2.718470853,"remaining_time":10.87388341},
{"learn":[0.04214167381],"iteration":200,"passed_time":2.730607758,"remaining_time":10.85450547},
{"learn":[0.04207198927],"iteration":201,"passed_time":2.746292654,"remaining_time":10.84921553},
{"learn":[0.04204292093],"iteration":202,"passed_time":2.759772497,"remaining_time":10.83516591},
{"learn":[0.04202678931],"iteration":203,"passed_time":2.773777695,"remaining_time":10.82317179},
{"learn":[0.04194948641],"iteration":204,"passed_time":2.779573228,"remaining_time":10.77932057},
{"learn":[0.04193325183],"iteration":205,"passed_time":2.794031651,"remaining_time":10.76922879},
{"learn":[0.04187143893],"iteration":206,"passed_time":2.811625545,"remaining_time":10.77110656},
{"learn":[0.04179110674],"iteration":207,"passed_time":2.818693098,"remaining_time":10.73271603},
{"learn":[0.0417162225],"iteration":208,"passed_time":2.829753133,"remaining_time":10.70973554},
{"learn":[0.04169492265],"iteration":209,"passed_time":2.842762285,"remaining_time":10.69420098},
{"learn":[0.04163051541],"iteration":210,"passed_time":2.855073287,"remaining_time":10.67607973},
{"learn":[0.04154810753],"iteration":211,"passed_time":2.86675472,"remaining_time":10.6556732},
{"learn":[0.0415334327],"iteration":212,"passed_time":2.882973832,"remaining_time":10.65211458},
{"learn":[0.04151997921],"iteration":213,"passed_time":2.890968348,"remaining_time":10.61822954},
{"learn":[0.04150313165],"iteration":214,"passed_time":2.90060212,"remaining_time":10.59057053},
{"learn":[0.0414457455],"iteration":215,"passed_time":2.916758429,"remaining_time":10.58675282},
{"learn":[0.04142787263],"iteration":216,"passed_time":2.929545839,"remaining_time":10.5706654},
{"learn":[0.04141528212],"iteration":217,"passed_time":2.937497059,"remaining_time":10.53726009},
{"learn":[0.0413336902],"iteration":218,"passed_time":2.946399037,"remaining_time":10.50747784},
{"learn":[0.04131786474],"iteration":219,"passed_time":2.957883799,"remaining_time":10.48704256},
{"learn":[0.04123470562],"iteration":220,"passed_time":2.967210128,"remaining_time":10.45908004},
{"learn":[0.04121067816],"iteration":221,"passed_time":2.975530171,"remaining_time":10.42775889},
{"learn":[0.04115561409],"iteration":222,"passed_time":2.985340963,"remaining_time":10.40183824},
{"learn":[0.04114210436],"iteration":223,"passed_time":2.998656072,"remaining_time":10.38820139},
{"learn":[0.0410598211],"iteration":224,"passed_time":3.007056843,"remaining_time":10.35764024},
{"learn":[0.04099426704],"iteration":225,"passed_time":3.030492201,"remaining_time":10.37876532},
{"learn":[0.04097736321],"iteration":226,"passed_time":3.039584045,"remaining_time":10.35065404},
{"learn":[0.04095721508],"iteration":227,"passed_time":3.048564375,"remaining_time":10.32233201},
{"learn":[0.04088925532],"iteration":228,"passed_time":3.053714347,"remaining_time":10.2812828},
{"learn":[0.04083716175],"iteration":229,"passed_time":3.062981289,"remaining_time":10.25432866},
{"learn":[0.040774373],"iteration":230,"passed_time":3.072808574,"remaining_time":10.22939304},
{"learn":[0.04072146977],"iteration":231,"passed_time":3.076398196,"remaining_time":10.18393886},
{"learn":[0.0406305211],"iteration":232,"passed_time":3.091252028,"remaining_time":10.17592406},
{"learn":[0.04050680763],"iteration":233,"passed_time":3.102263557,"remaining_time":10.15527301},
{"learn":[0.04044170386],"iteration":234,"passed_time":3.11583861,"remaining_time":10.14304909},
{"learn":[0.04039092223],"iteration":235,"passed_time":3.125639788,"remaining_time":10.1185966},
{"learn":[0.04032137988],"iteration":236,"passed_time":3.135142946,"remaining_time":10.0933083},
{"learn":[0.04028774875],"iteration":237,"passed_time":3.143228989,"remaining_time":10.0636155},
{"learn":[0.04023919744],"iteration":238,"passed_time":3.152084668,"remaining_time":10.03655411},
{"learn":[0.04019311136],"iteration":239,"passed_time":3.161174057,"remaining_time":10.01038451},
{"learn":[0.04012154131],"iteration":240,"passed_time":3.172039081,"remaining_time":9.989948806},
{"learn":[0.04010811002],"iteration":241,"passed_time":3.186179083,"remaining_time":9.979850187},
{"learn":[0.04003734724],"iteration":242,"passed_time":3.196843719,"remaining_time":9.958891749},
{"learn":[0.04002446745],"iteration":243,"passed_time":3.203916836,"remaining_time":9.926889868},
{"learn":[0.03996383727],"iteration":244,"passed_time":3.214306471,"remaining_time":9.905311778},
{"learn":[0.03990086134],"iteration":245,"passed_time":3.220343645,"remaining_time":9.870484182},
{"learn":[0.03983867406],"iteration":246,"passed_time":3.230147269,"remaining_time":9.84737204},
{"learn":[0.03982155759],"iteration":247,"passed_time":3.241346154,"remaining_time":9.828598015},
{"learn":[0.03976892619],"iteration":248,"passed_time":3.249195294,"remaining_time":9.799781789},
{"learn":[0.03972014271],"iteration":249,"passed_time":3.263383781,"remaining_time":9.790151343},
{"learn":[0.03966952066],"iteration":250,"passed_time":3.275826657,"remaining_time":9.775275563},
{"learn":[0.03956489328],"iteration":251,"passed_time":3.285598563,"remaining_time":9.752490973},
{"learn":[0.03948103427],"iteration":252,"passed_time":3.299993279,"remaining_time":9.743458416},
{"learn":[0.03940941471],"iteration":253,"passed_time":3.315893079,"remaining_time":9.738804083},
{"learn":[0.03939409531],"iteration":254,"passed_time":3.325893367,"remaining_time":9.716825719},
{"learn":[0.03937758939],"iteration":255,"passed_time":3.336213147,"remaining_time":9.695869458},
{"learn":[0.03929203416],"iteration":256,"passed_time":3.353336261,"remaining_time":9.694664753},
{"learn":[0.03927439062],"iteration":257,"passed_time":3.357008075,"remaining_time":9.654651132},
{"learn":[0.03922495055],"iteration":258,"passed_time":3.360799006,"remaining_time":9.615258931},
{"learn":[0.03917456575],"iteration":259,"passed_time":3.364185262,"remaining_time":9.574988823},
{"learn":[0.03913398917],"iteration":260,"passed_time":3.367715548,"remaining_time":9.535409156},
{"learn":[0.03907753683],"iteration":261,"passed_time":3.370594501,"remaining_time":9.494270008},
{"learn":[0.03905626001],"iteration":262,"passed_time":3.373258372,"remaining_time":9.452819088},
{"learn":[0.03896356479],"iteration":263,"passed_time":3.376198235,"remaining_time":9.412431444},
{"learn":[0.03891550226],"iteration":264,"passed_time":3.378987969,"remaining_time":9.371910028},
{"learn":[0.03890530037],"iteration":265,"passed_time":3.382230143,"remaining_time":9.332920771},
{"learn":[0.03882995151],"iteration":266,"passed_time":3.385429939,"remaining_time":9.294082942},
{"learn":[0.03877181255],"iteration":267,"passed_time":3.389231149,"remaining_time":9.257153735},
{"learn":[0.03874873957],"iteration":268,"passed_time":3.392768822,"remaining_time":9.219754679},
{"learn":[0.0386439862],"iteration":269,"passed_time":3.396338368,"remaining_time":9.1826926,
{,
{"learn":[0.0386338828],"iteration":270,"passed_time":3.400273805,"remaining_time":9.14686200,
,
{"learn":[0.03853024392],"iteration":271,"passed_time":3.404723733,"remaining_time":9.112642932},
{"learn":[0.03845510441],"iteration":272,"passed_time":3.409138175,"remaining_time":9.07854744,
{"learn":[0.03831175309],"iteration":273,"passed_time":3.485421329,"remaining_time":9.23509447},
{"learn":[0.03829736455],"iteration":274,"passed_time":3.493742254,"remaining_time":9.210775033},
{"learn":[0.0382301027],"iteration":275,"passed_time":3.50111036,"remaining_time":9.184072103},
{"learn":[0.03818008687],"iteration":276,"passed_time":3.514149895,"remaining_time":9.17231182},
{"learn":[0.03815586124],"iteration":277,"passed_time":3.525793836,"remaining_time":9.156917804},
{"learn":[0.03810559534],"iteration":278,"passed_time":3.534004694,"remaining_time":9.132678797},
{"learn":[0.03809559988],"iteration":279,"passed_time":3.544031039,"remaining_time":9.113222671},
{"learn":[0.03808587046],"iteration":280,"passed_time":3.55204134,"remaining_time":9.088675171},
{"learn":[0.0380375225],"iteration":281,"passed_time":3.558865477,"remaining_time":9.061224867},
{"learn":[0.03800070591],"iteration":282,"passed_time":3.570262135,"remaining_time":9.045505126},
{"learn":[0.0379496996],"iteration":283,"passed_time":3.582902904,"remaining_time":9.032952392},
{"learn":[0.03787709222],"iteration":284,"passed_time":3.591155871,"remaining_time":9.009391044},
{"learn":[0.03781690268],"iteration":285,"passed_time":3.5995968,"remaining_time":8.986405998},
{"learn":[0.03774948177],"iteration":286,"passed_time":3.611252628,"remaining_time":8.971509141},
{"learn":[0.03770883962],"iteration":287,"passed_time":3.620465798,"remaining_time":8.950596},
{"learn":[0.037650931],"iteration":288,"passed_time":3.626051852,"remaining_time":8.920840369},
{"learn":[0.03757796489],"iteration":289,"passed_time":3.63260223,"remaining_time":8.893612355},
{"learn":[0.03753407526],"iteration":290,"passed_time":3.639400932,"remaining_time":8.867131481},
{"learn":[0.03744178616],"iteration":291,"passed_time":3.65214673,"remaining_time":8.855205084},
{"learn":[0.03738717739],"iteration":292,"passed_time":3.658899943,"remaining_time":8.828813174},
{"learn":[0.03730126568],"iteration":293,"passed_time":3.665904495,"remaining_time":8.803158413},
{"learn":[0.03725288758],"iteration":294,"passed_time":3.677079901,"remaining_time":8.787597728},
{"learn":[0.03721253526],"iteration":295,"passed_time":3.686991467,"remaining_time":8.769060787},
{"learn":[0.0371540355],"iteration":296,"passed_time":3.70175178,"remaining_time":8.762058928},
{"learn":[0.03709552886],"iteration":297,"passed_time":3.712386558,"remaining_time":8.745286454},
{"learn":[0.03708592744],"iteration":298,"passed_time":3.729646315,"remaining_time":8.74408718},
{"learn":[0.03701758169],"iteration":299,"passed_time":3.735870945,"remaining_time":8.717032205},
{"learn":[0.03695714926],"iteration":300,"passed_time":3.751488986,"remaining_time":8.711929571},
{"learn":[0.03689593632],"iteration":301,"passed_time":3.760302951,"remaining_time":8.691031324},
{"learn":[0.03684697044],"iteration":302,"passed_time":3.776567016,"remaining_time":8.687350528},
{"learn":[0.03678326816],"iteration":303,"passed_time":3.783235233,"remaining_time":8.661617508},
{"learn":[0.03673699639],"iteration":304,"passed_time":3.805036926,"remaining_time":8.670493979},
{"learn":[0.03667861998],"iteration":305,"passed_time":3.81798745,"remaining_time":8.65909572},
{"learn":[0.03667014664],"iteration":306,"passed_time":3.834030029,"remaining_time":8.654667134},
{"learn":[0.03660762829],"iteration":307,"passed_time":3.845862972,"remaining_time":8.640705118},
{"learn":[0.03655569098],"iteration":308,"passed_time":3.858172218,"remaining_time":8.627822016},
{"learn":[0.03650206118],"iteration":309,"passed_time":3.870668841,"remaining_time":8.615359677},
{"learn":[0.03641648197],"iteration":310,"passed_time":3.881336182,"remaining_time":8.598844467},
{"learn":[0.03639022713],"iteration":311,"passed_time":3.896705769,"remaining_time":8.592735797},
{"learn":[0.0363113885],"iteration":312,"passed_time":3.903819466,"remaining_time":8.568447199},
{"learn":[0.03627247638],"iteration":313,"passed_time":3.912504221,"remaining_time":8.547700305},
{"learn":[0.03624872812],"iteration":314,"passed_time":3.921359592,"remaining_time":8.527401016},
{"learn":[0.03623920769],"iteration":315,"passed_time":3.929078069,"remaining_time":8.50471329},
{"learn":[0.03617761648],"iteration":316,"passed_time":3.933883662,"remaining_time":8.475843979},
{"learn":[0.03613354038],"iteration":317,"passed_time":3.945709235,"remaining_time":8.462181441},
{"learn":[0.03612481487],"iteration":318,"passed_time":3.956941526,"remaining_time":8.447263884},
{"learn":[0.0360530907],"iteration":319,"passed_time":3.965794833,"remaining_time":8.42731402},
{"learn":[0.03597030179],"iteration":320,"passed_time":3.973907779,"remaining_time":8.405867234},
{"learn":[0.03596414305],"iteration":321,"passed_time":3.987796477,"remaining_time":8.396664632},
{"learn":[0.0359195635],"iteration":322,"passed_time":4.003099825,"remaining_time":8.390398085},
{"learn":[0.0358375818],"iteration":323,"passed_time":4.014266607,"remaining_time":8.375445143},
{"learn":[0.0357614059],"iteration":324,"passed_time":4.024994223,"remaining_time":8.359603386},
{"learn":[0.03570688966],"iteration":325,"passed_time":4.0354274,"remaining_time":8.343184255},
{"learn":[0.03568046188],"iteration":326,"passed_time":4.049312061,"remaining_time":8.333905252},
{"learn":[0.03563244325],"iteration":327,"passed_time":4.059441487,"remaining_time":8.31690451},
{"learn":[0.03554764652],"iteration":328,"passed_time":4.070304322,"remaining_time":8.301441337},
{"learn":[0.03550019755],"iteration":329,"passed_time":4.076810524,"remaining_time":8.277160762},
{"learn":[0.0354497501],"iteration":330,"passed_time":4.08615427,"remaining_time":8.258722679},
{"learn":[0.03538951365],"iteration":331,"passed_time":4.095679002,"remaining_time":8.240703534},
{"learn":[0.03531071692],"iteration":332,"passed_time":4.101146204,"remaining_time":8.214608162},
{"learn":[0.03530686671],"iteration":333,"passed_time":4.111597062,"remaining_time":8.198573783},
{"learn":[0.03529128312],"iteration":334,"passed_time":4.120718803,"remaining_time":8.17993434},
{"learn":[0.03525360374],"iteration":335,"passed_time":4.12702262,"remaining_time":8.155782796},
{"learn":[0.03518639405],"iteration":336,"passed_time":4.137659443,"remaining_time":8.140261753},
{"learn":[0.03515297769],"iteration":337,"passed_time":4.147111103,"remaining_time":8.122448373},
{"learn":[0.03509845191],"iteration":338,"passed_time":4.163848489,"remaining_time":8.118890416},
{"learn":[0.03504153774],"iteration":339,"passed_time":4.174139292,"remaining_time":8.102740978},
{"learn":[0.03498453802],"iteration":340,"passed_time":4.179513925,"remaining_time":8.077125151},
{"learn":[0.03496720838],"iteration":341,"passed_time":4.189332032,"remaining_time":8.060176833},
{"learn":[0.03487414747],"iteration":342,"passed_time":4.20623661,"remaining_time":8.056843885},
{"learn":[0.03482936181],"iteration":343,"passed_time":4.212634811,"remaining_time":8.033396617},
{"learn":[0.0347760657],"iteration":344,"passed_time":4.221250031,"remaining_time":8.014257306},
{"learn":[0.03474862613],"iteration":345,"passed_time":4.227877206,"remaining_time":7.991421078},
{"learn":[0.03467443888],"iteration":346,"passed_time":4.239253839,"remaining_time":7.977616015},
{"learn":[0.03463260876],"iteration":347,"passed_time":4.245448837,"remaining_time":7.954116786},
{"learn":[0.03459328749],"iteration":348,"passed_time":4.25522832,"remaining_time":7.93740297},
{"learn":[0.03452584727],"iteration":349,"passed_time":4.261350049,"remaining_time":7.913935805},
{"learn":[0.0344765713],"iteration":350,"passed_time":4.271068903,"remaining_time":7.897218569},
{"learn":[0.03441905674],"iteration":351,"passed_time":4.277162778,"remaining_time":7.873867842},
{"learn":[0.03434953874],"iteration":352,"passed_time":4.284044606,"remaining_time":7.852059094},
{"learn":[0.03427805618],"iteration":353,"passed_time":4.291184032,"remaining_time":7.830804758},
{"learn":[0.03427189422],"iteration":354,"passed_time":4.299919723,"remaining_time":7.812530201},
{"learn":[0.03421562101],"iteration":355,"passed_time":4.310017426,"remaining_time":7.796773097},
{"learn":[0.03418740723],"iteration":356,"passed_time":4.32223605,"remaining_time":7.784867732},
{"learn":[0.03412150172],"iteration":357,"passed_time":4.335154762,"remaining_time":7.774216081},
{"learn":[0.03406773384],"iteration":358,"passed_time":4.341127871,"remaining_time":7.751150321},
{"learn":[0.03399593999],"iteration":359,"passed_time":4.348947429,"remaining_time":7.731462096},
{"learn":[0.03394452147],"iteration":360,"passed_time":4.360293488,"remaining_time":7.718081825},
{"learn":[0.03391411],"iteration":361,"passed_time":4.367319457,"remaining_time":7.697098932},
{"learn":[0.0339060634],"iteration":362,"passed_time":4.375517807,"remaining_time":7.678250257},
{"learn":[0.03384143324],"iteration":363,"passed_time":4.387985306,"remaining_time":7.66691938},
{"learn":[0.03382464242],"iteration":364,"passed_time":4.396115091,"remaining_time":7.648035843},
{"learn":[0.03378118186],"iteration":365,"passed_time":4.405397242,"remaining_time":7.631207244},
{"learn":[0.03373611919],"iteration":366,"passed_time":4.416612317,"remaining_time":7.617753669},
{"learn":[0.03366187286],"iteration":367,"passed_time":4.426269268,"remaining_time":7.601636352},
{"learn":[0.03364052327],"iteration":368,"passed_time":4.432238346,"remaining_time":7.579247687},
{"learn":[0.03358043932],"iteration":369,"passed_time":4.439062628,"remaining_time":7.558403935},
{"learn":[0.03357682731],"iteration":370,"passed_time":4.448566887,"remaining_time":7.542179439},
{"learn":[0.03354867237],"iteration":371,"passed_time":4.456945236,"remaining_time":7.524090345},
{"learn":[0.03347847716],"iteration":372,"passed_time":4.460888134,"remaining_time":7.49859748},
{"learn":[0.03339814311],"iteration":373,"passed_time":4.470613903,"remaining_time":7.482899207},
{"learn":[0.03333957237],"iteration":374,"passed_time":4.483965012,"remaining_time":7.473275021},
{"learn":[0.03332004955],"iteration":375,"passed_time":4.496280138,"remaining_time":7.461911718},
{"learn":[0.03326026675],"iteration":376,"passed_time":4.507760543,"remaining_time":7.449163975},
{"learn":[0.03324808099],"iteration":377,"passed_time":4.523501124,"remaining_time":7.443433067},
{"learn":[0.03321493629],"iteration":378,"passed_time":4.529063594,"remaining_time":7.420972275},
{"learn":[0.03317216329],"iteration":379,"passed_time":4.539693837,"remaining_time":7.406868891},
{"learn":[0.03314599435],"iteration":380,"passed_time":4.545761319,"remaining_time":7.385370752},
{"learn":[0.03310364529],"iteration":381,"passed_time":4.556453828,"remaining_time":7.371435773},
{"learn":[0.03306925573],"iteration":382,"passed_time":4.564306835,"remaining_time":7.352943387},
{"learn":[0.03305539961],"iteration":383,"passed_time":4.572004639,"remaining_time":7.334257441},
{"learn":[0.03304772825],"iteration":384,"passed_time":4.581694873,"remaining_time":7.318811291},
{"learn":[0.03304435013],"iteration":385,"passed_time":4.592961384,"remaining_time":7.305902305},
{"learn":[0.03299095325],"iteration":386,"passed_time":4.600815689,"remaining_time":7.287596943},
{"learn":[0.03297504945],"iteration":387,"passed_time":4.610588755,"remaining_time":7.272371953},
{"learn":[0.03292718533],"iteration":388,"passed_time":4.626732464,"remaining_time":7.267181326},
{"learn":[0.03290893728],"iteration":389,"passed_time":4.636724485,"remaining_time":7.252312656},
{"learn":[0.0328891537],"iteration":390,"passed_time":4.645453151,"remaining_time":7.2355012},
{"learn":[0.03286426478],"iteration":391,"passed_time":4.652602641,"remaining_time":7.216281647},
{"learn":[0.03283994284],"iteration":392,"passed_time":4.663475333,"remaining_time":7.202874115},
{"learn":[0.03281845171],"iteration":393,"passed_time":4.672169481,"remaining_time":7.186128694},
{"learn":[0.03279877704],"iteration":394,"passed_time":4.677990481,"remaining_time":7.165023395},
{"learn":[0.03276705754],"iteration":395,"passed_time":4.686956767,"remaining_time":7.148792645},
{"learn":[0.03273650115],"iteration":396,"passed_time":4.689932592,"remaining_time":7.12349963},
{"learn":[0.03266778561],"iteration":397,"passed_time":4.69921427,"remaining_time":7.10785676},
{"learn":[0.03265331816],"iteration":398,"passed_time":4.713388801,"remaining_time":7.099615712},
{"learn":[0.03261873646],"iteration":399,"passed_time":4.721160792,"remaining_time":7.081741188},
{"learn":[0.03261034131],"iteration":400,"passed_time":4.730634992,"remaining_time":7.066459752},
{"learn":[0.03255503242],"iteration":401,"passed_time":4.740938464,"remaining_time":7.0524408},
{"learn":[0.03248614071],"iteration":402,"passed_time":4.751929401,"remaining_time":7.039458691},
{"learn":[0.03247295439],"iteration":403,"passed_time":4.761269895,"remaining_time":7.024051628},
{"learn":[0.03246493666],"iteration":404,"passed_time":4.772836202,"remaining_time":7.011944544},
{"learn":[0.0324196762],"iteration":405,"passed_time":4.788905653,"remaining_time":7.006428468},
{"learn":[0.03239943054],"iteration":406,"passed_time":4.801769472,"remaining_time":6.996189918},
{"learn":[0.03234223953],"iteration":407,"passed_time":4.813963461,"remaining_time":6.984966591},
{"learn":[0.03227549628],"iteration":408,"passed_time":4.829120664,"remaining_time":6.978020323},
{"learn":[0.03218155039],"iteration":409,"passed_time":4.838780326,"remaining_time":6.963122908},
{"learn":[0.0321754022],"iteration":410,"passed_time":4.85058191,"remaining_time":6.951320548},
{"learn":[0.03213379463],"iteration":411,"passed_time":4.857695384,"remaining_time":6.932827393},
{"learn":[0.03207800634],"iteration":412,"passed_time":4.867478165,"remaining_time":6.918183251},
{"learn":[0.0320436315],"iteration":413,"passed_time":4.877226325,"remaining_time":6.903513591},
{"learn":[0.03199783635],"iteration":414,"passed_time":4.884083926,"remaining_time":6.884793004},
{"learn":[0.03191685795],"iteration":415,"passed_time":4.892939126,"remaining_time":6.868933773},
{"learn":[0.03190542973],"iteration":416,"passed_time":4.903477623,"remaining_time":6.855461521},
{"learn":[0.03189749557],"iteration":417,"passed_time":4.912342532,"remaining_time":6.839673094},
{"learn":[0.03186463219],"iteration":418,"passed_time":4.921702,"remaining_time":6.82460349},
{"learn":[0.03181104487],"iteration":419,"passed_time":4.930840778,"remaining_time":6.809256313},
{"learn":[0.03174745478],"iteration":420,"passed_time":4.939276159,"remaining_time":6.792971249},
{"learn":[0.03172778402],"iteration":421,"passed_time":4.950717443,"remaining_time":6.780840478},
{"learn":[0.03168314839],"iteration":422,"passed_time":4.962773239,"remaining_time":6.769551204},
{"learn":[0.0316284302],"iteration":423,"passed_time":4.971758655,"remaining_time":6.75408723},
{"learn":[0.03161150441],"iteration":424,"passed_time":4.979627278,"remaining_time":6.737142788},
{"learn":[0.03156823581],"iteration":425,"passed_time":4.992696306,"remaining_time":6.727248074},
{"learn":[0.03156465943],"iteration":426,"passed_time":5.003067413,"remaining_time":6.713718097},
{"learn":[0.03155504481],"iteration":427,"passed_time":5.007821429,"remaining_time":6.692695929},
{"learn":[0.03152664583],"iteration":428,"passed_time":5.017859216,"remaining_time":6.678782314},
{"learn":[0.03150311654],"iteration":429,"passed_time":5.027231946,"remaining_time":6.664005138},
{"learn":[0.03149273273],"iteration":430,"passed_time":5.038133422,"remaining_time":6.651271269},
{"learn":[0.03145912974],"iteration":431,"passed_time":5.042751467,"remaining_time":6.630284336},
{"learn":[0.03144459155],"iteration":432,"passed_time":5.048153542,"remaining_time":6.610399673},
{"learn":[0.03140279491],"iteration":433,"passed_time":5.052328292,"remaining_time":6.588981136},
{"learn":[0.03138733209],"iteration":434,"passed_time":5.055970531,"remaining_time":6.566950229},
{"learn":[0.03136595255],"iteration":435,"passed_time":5.061152949,"remaining_time":6.546996016},
{"learn":[0.03133692399],"iteration":436,"passed_time":5.064872138,"remaining_time":6.525224288},
{"learn":[0.03132199285],"iteration":437,"passed_time":5.069571448,"remaining_time":6.504792589},
{"learn":[0.03128035169],"iteration":438,"passed_time":5.077233393,"remaining_time":6.488218527},
{"learn":[0.03124602348],"iteration":439,"passed_time":5.084127857,"remaining_time":6.470708182},
{"learn":[0.03118641988],"iteration":440,"passed_time":5.088557229,"remaining_time":6.450121295},
{"learn":[0.03114427633],"iteration":441,"passed_time":5.094787263,"remaining_time":6.431880752},
{"learn":[0.03112785204],"iter,
{"learn":[0.03081765303],"iteration":442,"passed_time":5.0084884,
{"learn":[0.03112486976],"iter,
{"learn":[0.03079491546],"iteration":443,"passed_time":5.015661,
{"learn":[0.03108063964],"itera,
{"learn":[0.0307912685],"iteration":444,"passed_time":5.023739488,"remaining_time":6.265562732},
{"learn":[0.03077099562],"iteration":445,"passed_time":5.034470002,"remaining_time":6.25357933},
{"learn":[0.03075007784],"iteration":446,"passed_time":5.04322041,"remaining_time":6.239151872},
{"learn":[0.03071256807],"iteration":447,"passed_time":5.051334734,"remaining_time":6.223966012},
{"learn":[0.0306941417],"iteration":448,"passed_time":5.064297401,"remaining_time":6.214761398},
{"learn":[0.03067551496],"iteration":449,"passed_time":5.075195452,"remaining_time":6.203016664},
{"learn":[0.03063231145],"iteration":450,"passed_time":5.082219198,"remaining_time":6.186559511},
{"learn":[0.03062866156],"iteration":451,"passed_time":5.088156308,"remaining_time":6.168826674},
{"learn":[0.03060412196],"iteration":452,"passed_time":5.098081685,"remaining_time":6.15596177},
{"learn":[0.03056860327],"iteration":453,"passed_time":5.104013753,"remaining_time":6.138307289},
{"learn":[0.03056067272],"iteration":454,"passed_time":5.109938201,"remaining_time":6.120695208},
{"learn":[0.03053851791],"iteration":455,"passed_time":5.118017262,"remaining_time":6.105704804},
{"learn":[0.0305218158],"iteration":456,"passed_time":5.132689764,"remaining_time":6.098578867},
{"learn":[0.03051386396],"iteration":457,"passed_time":5.142440655,"remaining_time":6.08559571},
{"learn":[0.03046015161],"iteration":458,"passed_time":5.151137957,"remaining_time":6.071384825},
{"learn":[0.03042403132],"iteration":459,"passed_time":5.157870165,"remaining_time":6.054891064},
{"learn":[0.03038928127],"iteration":460,"passed_time":5.170757033,"remaining_time":6.045635663},
{"learn":[0.03038049813],"iteration":461,"passed_time":5.176105817,"remaining_time":6.027586427},
{"learn":[0.03032222173],"iteration":462,"passed_time":5.181743234,"remaining_time":6.009926818},
{"learn":[0.03029901409],"iteration":463,"passed_time":5.192736952,"remaining_time":5.998506479},
{"learn":[0.03027586526],"iteration":464,"passed_time":5.203806796,"remaining_time":5.987175561},
{"learn":[0.03026355487],"iteration":465,"passed_time":5.216793754,"remaining_time":5.978042628},
{"learn":[0.03024695223],"iteration":466,"passed_time":5.224806878,"remaining_time":5.963216415},
{"learn":[0.03019578689],"iteration":467,"passed_time":5.234831941,"remaining_time":5.950706395},
{"learn":[0.03017637143],"iteration":468,"passed_time":5.244474376,"remaining_time":5.937773761},
{"learn":[0.03013584425],"iteration":469,"passed_time":5.250137686,"remaining_time":5.920368029},
{"learn":[0.0301108368],"iteration":470,"passed_time":5.265523365,"remaining_time":5.913931762},
{"learn":[0.03008902566],"iteration":471,"passed_time":5.268778462,"remaining_time":5.893887771},
{"learn":[0.03006001797],"iteration":472,"passed_time":5.280335899,"remaining_time":5.883164944},
{"learn":[0.03003737338],"iteration":473,"passed_time":5.288848686,"remaining_time":5.869059934},
{"learn":[0.03001857178],"iteration":474,"passed_time":5.292205332,"remaining_time":5.849279577},
{"learn":[0.03000702429],"iteration":475,"passed_time":5.297763272,"remaining_time":5.831991501},
{"learn":[0.02997737935],"iteration":476,"passed_time":5.308187545,"remaining_time":5.820088231},
{"learn":[0.02995267296],"iteration":477,"passed_time":5.319801911,"remaining_time":5.809490789},
{"learn":[0.02993183308],"iteration":478,"passed_time":5.329029725,"remaining_time":5.796293292},
{"learn":[0.02990728723],"iteration":479,"passed_time":5.333103007,"remaining_time":5.777528258},
{"learn":[0.0298936506],"iteration":480,"passed_time":5.339624499,"remaining_time":5.761465935},
{"learn":[0.02986189204],"iteration":481,"passed_time":5.347484878,"remaining_time":5.746882089},
{"learn":[0.02981288656],"iteration":482,"passed_time":5.353638261,"remaining_time":5.730498925},
{"learn":[0.02977547976],"iteration":483,"passed_time":5.366396409,"remaining_time":5.721199477},
{"learn":[0.0297065874],"iteration":484,"passed_time":5.380456925,"remaining_time":5.713268694},
{"learn":[0.02965212102],"iteration":485,"passed_time":5.387318027,"remaining_time":5.697698489},
{"learn":[0.02963193745],"iteration":486,"passed_time":5.396650845,"remaining_time":5.684767728},
{"learn":[0.02961375835],"iteration":487,"passed_time":5.404538165,"remaining_time":5.670335124},
{"learn":[0.02957977985],"iteration":488,"passed_time":5.411208447,"remaining_time":5.654657498},
{"learn":[0.0295543924],"iteration":489,"passed_time":5.421948976,"remaining_time":5.643253016},
{"learn":[0.02951471104],"iteration":490,"passed_time":5.424909437,"remaining_time":5.623785954},
{"learn":[0.02948573489],"iteration":491,"passed_time":5.431768964,"remaining_time":5.608411857},
{"learn":[0.02947772816],"iteration":492,"passed_time":5.442948718,"remaining_time":5.597515213},
{"learn":[0.02944336629],"iteration":493,"passed_time":5.457680213,"remaining_time":5.590255441},
{"learn":[0.02944048526],"iteration":494,"passed_time":5.468899835,"remaining_time":5.57938266},
{"learn":[0.02940753449],"iteration":495,"passed_time":5.477641372,"remaining_time":5.565990426},
{"learn":[0.02938709776],"iteration":496,"passed_time":5.489093158,"remaining_time":5.555359876},
{"learn":[0.02937127671],"iteration":497,"passed_time":5.508944882,"remaining_time":5.553193435},
{"learn":[0.0293565958],"iteration":498,"passed_time":5.525798754,"remaining_time":5.547946244},
{"learn":[0.02929826657],"iteration":499,"passed_time":5.535439586,"remaining_time":5.535439586},
{"learn":[0.02926808921],"iteration":500,"passed_time":5.543068118,"remaining_time":5.520940102},
{"learn":[0.02926360671],"iteration":501,"passed_time":5.554999511,"remaining_time":5.510736566},
{"learn":[0.02922827011],"iteration":502,"passed_time":5.562825875,"remaining_time":5.4964701},
{"learn":[0.02920358629],"iteration":503,"passed_time":5.570760095,"remaining_time":5.482335331},
{"learn":[0.02915271346],"iteration":504,"passed_time":5.576374035,"remaining_time":5.465950787},
{"learn":[0.02911282599],"iteration":505,"passed_time":5.593274731,"remaining_time":5.4606279},
{"learn":[0.0290834023],"iteration":506,"passed_time":5.603317644,"remaining_time":5.448590924},
{"learn":[0.02904224442],"iteration":507,"passed_time":5.612181499,"remaining_time":5.435419877},
{"learn":[0.02901778884],"iteration":508,"passed_time":5.621007369,"remaining_time":5.422229112},
{"learn":[0.02900938705],"iteration":509,"passed_time":5.633302247,"remaining_time":5.412388434},
{"learn":[0.02896052908],"iteration":510,"passed_time":5.646039902,"remaining_time":5.402961863},
{"learn":[0.02893583183],"iteration":511,"passed_time":5.65669465,"remaining_time":5.391537089},
{"learn":[0.02889443703],"iteration":512,"passed_time":5.666150984,"remaining_time":5.37897764},
{"learn":[0.02884548197],"iteration":513,"passed_time":5.676068587,"remaining_time":5.366866408},
{"learn":[0.02882999687],"iteration":514,"passed_time":5.684316727,"remaining_time":5.353191481},
{"learn":[0.02881010763],"iteration":515,"passed_time":5.692898342,"remaining_time":5.339850383},
{"learn":[0.02877021369],"iteration":516,"passed_time":5.703887022,"remaining_time":5.328776464},
{"learn":[0.02876862909],"iteration":517,"passed_time":5.710674168,"remaining_time":5.313793338},
{"learn":[0.02874270396],"iteration":518,"passed_time":5.720768155,"remaining_time":5.301906518},
{"learn":[0.02869481916],"iteration":519,"passed_time":5.728183171,"remaining_time":5.287553697},
{"learn":[0.02868749981],"iteration":520,"passed_time":5.738075624,"remaining_time":5.275505228},
{"learn":[0.02867026875],"iteration":521,"passed_time":5.745036297,"remaining_time":5.260780364},
{"learn":[0.02862046797],"iteration":522,"passed_time":5.751736593,"remaining_time":5.245847715},
{"learn":[0.02858493167],"iteration":523,"passed_time":5.760956309,"remaining_time":5.23323512},
{"learn":[0.02857574068],"iteration":524,"passed_time":5.769844293,"remaining_time":5.220335312},
{"learn":[0.02854739288],"iteration":525,"passed_time":5.778779284,"remaining_time":5.207493119},
{"learn":[0.02851503721],"iteration":526,"passed_time":5.786397732,"remaining_time":5.193484113},
{"learn":[0.02849606774],"iteration":527,"passed_time":5.792499826,"remaining_time":5.178143784},
{"learn":[0.02848681174],"iteration":528,"passed_time":5.799619384,"remaining_time":5.163744291},
{"learn":[0.02847548424],"iteration":529,"passed_time":5.812573126,"remaining_time":5.15454598},
{"learn":[0.02844877726],"iteration":530,"passed_time":5.820235952,"remaining_time":5.140660379},
{"learn":[0.02840411347],"iteration":531,"passed_time":5.828412714,"remaining_time":5.127250282},
{"learn":[0.02838880793],"iteration":532,"passed_time":5.839277396,"remaining_time":5.116214904},
{"learn":[0.02838444034],"iteration":533,"passed_time":5.850861478,"remaining_time":5.105807957},
{"learn":[0.02834719932],"iteration":534,"passed_time":5.860067732,"remaining_time":5.093329898},
{"learn":[0.02830204831],"iteration":535,"passed_time":5.869829923,"remaining_time":5.081345306},
{"learn":[0.02827474948],"iteration":536,"passed_time":5.878182748,"remaining_time":5.06815384},
{"learn":[0.02822275181],"iteration":537,"passed_time":5.893375253,"remaining_time":5.060853842},
{"learn":[0.02818006527],"iteration":538,"passed_time":5.913175499,"remaining_time":5.057465501},
{"learn":[0.02815621142],"iteration":539,"passed_time":5.928792743,"remaining_time":5.050453077},
{"learn":[0.02811285514],"iteration":540,"passed_time":5.939450037,"remaining_time":5.039200679},
{"learn":[0.02809121063],"iteration":541,"passed_time":5.949410658,"remaining_time":5.027361773},
{"learn":[0.02804824144],"iteration":542,"passed_time":5.959251104,"remaining_time":5.015428646},
{"learn":[0.02800195389],"iteration":543,"passed_time":5.973665756,"remaining_time":5.007337472},
{"learn":[0.02796983196],"iteration":544,"passed_time":5.98165888,"remaining_time":4.993862001},
{"learn":[0.02796708385],"iteration":545,"passed_time":5.990843052,"remaining_time":4.98139697},
{"learn":[0.0279235907],"iteration":546,"passed_time":6.002440521,"remaining_time":4.970942515},
{"learn":[0.02789461584],"iteration":547,"passed_time":6.009765469,"remaining_time":4.956959839},
{"learn":[0.0278633416],"iteration":548,"passed_time":6.021560285,"remaining_time":4.946673385},
{"learn":[0.02783229206],"iteration":549,"passed_time":6.029532332,"remaining_time":4.933253726},
{"learn":[0.02778355762],"iteration":550,"passed_time":6.041272284,"remaining_time":4.922924239},
{"learn":[0.02776690429],"iteration":551,"passed_time":6.0490964,"remaining_time":4.909411571},
{"learn":[0.02774859291],"iteration":552,"passed_time":6.058902816,"remaining_time":4.897521806},
{"learn":[0.02772971299],"iteration":553,"passed_time":6.070341568,"remaining_time":4.886953681},
{"learn":[0.02770519064],"iteration":554,"passed_time":6.078989471,"remaining_time":4.874144711},
{"learn":[0.02767447442],"iteration":555,"passed_time":6.087272806,"remaining_time":4.861059579},
{"learn":[0.02762962259],"iteration":556,"passed_time":6.09709629,"remaining_time":4.849216618},
{"learn":[0.02759451894],"iteration":557,"passed_time":6.105065642,"remaining_time":4.835912211},
{"learn":[0.0275539349],"iteration":558,"passed_time":6.112508737,"remaining_time":4.822211722},
{"learn":[0.02750737074],"iteration":559,"passed_time":6.119398154,"remaining_time":4.80809855},
{"learn":[0.02749115463],"iteration":560,"passed_time":6.129407439,"remaining_time":4.796452524},
{"learn":[0.02746504013],"iteration":561,"passed_time":6.13946632,"remaining_time":4.784850975},
{"learn":[0.02746212564],"iteration":562,"passed_time":6.146892261,"remaining_time":4.771211222},
{"learn":[0.02743229466],"iteration":563,"passed_time":6.1590952,"remaining_time":4.76128636},
{"learn":[0.02741827252],"iteration":564,"passed_time":6.165490001,"remaining_time":4.746881682},
{"learn":[0.02739378502],"iteration":565,"passed_time":6.169442911,"remaining_time":4.730632904},
{"learn":[0.02736410474],"iteration":566,"passed_time":6.178234153,"remaining_time":4.718122378},
{"learn":[0.02734387251],"iteration":567,"passed_time":6.187671524,"remaining_time":4.70611637},
{"learn":[0.02733139892],"iteration":568,"passed_time":6.197758718,"remaining_time":4.694611613},
{"learn":[0.02726614607],"iteration":569,"passed_time":6.20673222,"remaining_time":4.682271675},
{"learn":[0.027248662],"iteration":570,"passed_time":6.215520809,"remaining_time":4.669804601},
{"learn":[0.02720386801],"iteration":571,"passed_time":6.226083989,"remaining_time":4.658678229},
{"learn":[0.02720208206],"iteration":572,"passed_time":6.229281697,"remaining_time":4.642065069},
{"learn":[0.02717171172],"iteration":573,"passed_time":6.233626215,"remaining_time":4.62634977},
{"learn":[0.02712097893],"iteration":574,"passed_time":6.237643826,"remaining_time":4.610432393},
{"learn":[0.02711560616],"iteration":575,"passed_time":6.241177738,"remaining_time":4.594200279},
{"learn":[0.02708197314],"iteration":576,"passed_time":6.244950313,"remaining_time":4.578187145},
{"learn":[0.02708021777],"iteration":577,"passed_time":6.248395326,"remaining_time":4.56197721},
{"learn":[0.02705947403],"iteration":578,"passed_time":6.252851459,"remaining_time":4.54654657},
{"learn":[0.02704408478],"iteration":579,"passed_time":6.256446006,"remaining_time":4.530529867},
{"learn":[0.02702277921],"iteration":580,"passed_time":6.26004708,"remaining_time":4.514560631},
{"learn":[0.02700583223],"iteration":581,"passed_time":6.264971729,"remaining_time":4.499584507},
{"learn":[0.02696800229],"iteration":582,"passed_time":6.269224394,"remaining_time":4.484162217},
{"learn":[0.02693198184],"iteration":583,"passed_time":6.27250843,"remaining_time":4.468088197},
{"learn":[0.02691912536],"iteration":584,"passed_time":6.276882051,"remaining_time":4.452830857},
{"learn":[0.02688721319],"iteration":585,"passed_time":6.281061189,"remaining_time":4.437473263},
{"learn":[0.02686125249],"iteration":586,"passed_time":6.28508809,"remaining_time":4.422046646},
{"learn":[0.02681601538],"iteration":587,"passed_time":6.289378901,"remaining_time":4.40684372},
{"learn":[0.02679022038],"iteration":588,"passed_time":6.293193808,"remaining_time":4.391345764},
{"learn":[0.02674763694],"iteration":589,"passed_time":6.29700035,"remaining_time":4.375881599},
{"learn":[0.02672414678],"iteration":590,"passed_time":6.301584382,"remaining_time":4.360994944},
{"learn":[0.02668451447],"iteration":591,"passed_time":6.305120491,"remaining_time":4.345420879},
{"learn":[0.02664691737],"iteration":592,"passed_time":6.308677638,"remaining_time":4.329901853},
{"learn":[0.02663527674],"iteration":593,"passed_time":6.312674621,"remaining_time":4.314723731},
{"learn":[0.02661038156],"iteration":594,"passed_time":6.317642735,"remaining_time":4.300244214},
{"learn":[0.02659712981],"iteration":595,"passed_time":6.321571175,"remaining_time":4.28509187},
{"learn":[0.02658323017],"iteration":596,"passed_time":6.326385152,"remaining_time":4.270574901},
{"learn":[0.02658120028],"iteration":597,"passed_time":6.329552881,"remaining_time":4.254983709},
{"learn":[0.02655283449],"iteration":598,"passed_time":6.334390138,"remaining_time":4.240551662},
{"learn":[0.02652799957],"iteration":599,"passed_time":6.33859004,"remaining_time":4.225726693},
{"learn":[0.02646471663],"iteration":600,"passed_time":6.342876651,"remaining_time":4.210994649},
{"learn":[0.02641994593],"iteration":601,"passed_time":6.34714049,"remaining_time":4.196282251},
{"learn":[0.02641230364],"iteration":602,"passed_time":6.351155506,"remaining_time":4.18144069},
{"learn":[0.0263945144],"iteration":603,"passed_time":6.354908436,"remaining_time":4.166463147},
{"learn":[0.02637683171],"iteration":604,"passed_time":6.359181003,"remaining_time":4.151861977},
{"learn":[0.02635014546],"iteration":605,"passed_time":6.364302502,"remaining_time":4.137846841},
{"learn":[0.02631408856],"iteration":606,"passed_time":6.367779217,"remaining_time":4.122796099},
{"learn":[0.0262943098],"iteration":607,"passed_time":6.372151274,"remaining_time":4.10836069},
{"learn":[0.02628802779],"iteration":608,"passed_time":6.376102361,"remaining_time":4.093688051},
{"learn":[0.02625565163],"iteration":609,"passed_time":6.380201865,"remaining_time":4.079145455},
{"learn":[0.02624243467],"iteration":610,"passed_time":6.383847698,"remaining_time":4.064348207},
{"learn":[0.0261875111],"iteration":611,"passed_time":6.388872027,"remaining_time":4.05046135},
{"learn":[0.02616736532],"iteration":612,"passed_time":6.39287024,"remaining_time":4.0359556},
{"learn":[0.02615197382],"iteration":613,"passed_time":6.396490635,"remaining_time":4.021246556},
{"learn":[0.02614084919],"iteration":614,"passed_time":6.40112039,"remaining_time":4.007205447},
{"learn":[0.02612041151],"iteration":615,"passed_time":6.405642891,"remaining_time":3.993128036},
{"learn":[0.02611909033],"iteration":616,"passed_time":6.409770187,"remaining_time":3.978836275},
{"learn":[0.0260742999],"iteration":617,"passed_time":6.415297194,"remaining_time":3.965442602},
{"learn":[0.02605467972],"iteration":618,"passed_time":6.419760609,"remaining_time":3.951419696},
{"learn":[0.02604758029],"iteration":619,"passed_time":6.423477921,"remaining_time":3.936970339},
{"learn":[0.02601456978],"iteration":620,"passed_time":6.42803268,"remaining_time":3.923066644},
{"learn":[0.02600501758],"iteration":621,"passed_time":6.431824698,"remaining_time":3.908729479,
{"learn":[0.02654134331],"iteration":622,"passed_time":6.453202305,"remaining_time":3.905067847},
{"learn":[0.02650629211],"iteration":623,"passed_time":6.460809927,"remaining_time":3.893052135},
{"learn":[0.02647432701],"iteration":624,"passed_time":6.469381241,"remaining_time":3.881628744},
{"learn":[0.02645545113],"iteration":625,"passed_time":6.481811354,"remaining_time":3.872519882},
{"learn":[0.0264467698],"iteration":626,"passed_time":6.491772987,"remaining_time":3.861931937},
{"learn":[0.02644244386],"iteration":627,"passed_time":6.499880253,"remaining_time":3.850247539},
{"learn":[0.02641416069],"iteration":628,"passed_time":6.508980219,"remaining_time":3.839160034},
{"learn":[0.02639794752],"iteration":629,"passed_time":6.519682577,"remaining_time":3.829019926},
{"learn":[0.02636927719],"iteration":630,"passed_time":6.524416614,"remaining_time":3.815387846},
{"learn":[0.02632979719],"iteration":631,"passed_time":6.528343764,"remaining_time":3.801314091},
{"learn":[0.02631394682],"iteration":632,"passed_time":6.535724752,"remaining_time":3.789274856},
{"learn":[0.02629866609],"iteration":633,"passed_time":6.547463983,"remaining_time":3.779766274},
{"learn":[0.02626254307],"iteration":634,"passed_time":6.561147576,"remaining_time":3.771368292},
{"learn":[0.02624200312],"iteration":635,"passed_time":6.567766247,"remaining_time":3.758910242},
{"learn":[0.02620047078],"iteration":636,"passed_time":6.57472038,"remaining_time":3.746661692},
{"learn":[0.02617699545],"iteration":637,"passed_time":6.581940101,"remaining_time":3.734580434},
{"learn":[0.02613989889],"iteration":638,"passed_time":6.591030307,"remaining_time":3.723571112},
{"learn":[0.02610580744],"iteration":639,"passed_time":6.606445773,"remaining_time":3.716125747},
{"learn":[0.0261044851],"iteration":640,"passed_time":6.618648912,"remaining_time":3.706856411},
{"learn":[0.02608840267],"iteration":641,"passed_time":6.622638124,"remaining_time":3.692997583},
{"learn":[0.0260626056],"iteration":642,"passed_time":6.632657467,"remaining_time":3.682517443},
{"learn":[0.02603239582],"iteration":643,"passed_time":6.64772218,"remaining_time":3.674827789},
{"learn":[0.02601707945],"iteration":644,"passed_time":6.65750874,"remaining_time":3.664210237},
{"learn":[0.02601562641],"iteration":645,"passed_time":6.665434962,"remaining_time":3.652575815},
{"learn":[0.02597418845],"iteration":646,"passed_time":6.673436516,"remaining_time":3.640993957},
{"learn":[0.0259106768],"iteration":647,"passed_time":6.679185377,"remaining_time":3.628199464},
{"learn":[0.02586751468],"iteration":648,"passed_time":6.687915909,"remaining_time":3.617039267},
{"learn":[0.02584034881],"iteration":649,"passed_time":6.705162775,"remaining_time":3.610472264},
{"learn":[0.02582715387],"iteration":650,"passed_time":6.713155735,"remaining_time":3.598911446},
{"learn":[0.02578296301],"iteration":651,"passed_time":6.719620346,"remaining_time":3.586545829},
{"learn":[0.02574445699],"iteration":652,"passed_time":6.731472713,"remaining_time":3.577061304},
{"learn":[0.02571237964],"iteration":653,"passed_time":6.741241973,"remaining_time":3.566467466},
{"learn":[0.02569287458],"iteration":654,"passed_time":6.747952854,"remaining_time":3.554265244},
{"learn":[0.02565796553],"iteration":655,"passed_time":6.754706146,"remaining_time":3.542102003},
{"learn":[0.02564607656],"iteration":656,"passed_time":6.762373676,"remaining_time":3.530432528},
{"learn":[0.02560987245],"iteration":657,"passed_time":6.773236702,"remaining_time":3.520436097},
{"learn":[0.02557375998],"iteration":658,"passed_time":6.781487931,"remaining_time":3.509085561},
{"learn":[0.02551475103],"iteration":659,"passed_time":6.785741682,"remaining_time":3.495685109},
{"learn":[0.02547842554],"iteration":660,"passed_time":6.79014744,"remaining_time":3.48239029},
{"learn":[0.02545032524],"iteration":661,"passed_time":6.806834943,"remaining_time":3.475393067},
{"learn":[0.02542185036],"iteration":662,"passed_time":6.816023709,"remaining_time":3.464555038},
{"learn":[0.02538418219],"iteration":663,"passed_time":6.826713348,"remaining_time":3.454481453},
{"learn":[0.02536932959],"iteration":664,"passed_time":6.833911125,"remaining_time":3.442646958},
{"learn":[0.02534761791],"iteration":665,"passed_time":6.845286697,"remaining_time":3.432921557},
{"learn":[0.0253262052],"iteration":666,"passed_time":6.855326385,"remaining_time":3.422524267},
{"learn":[0.02529351733],"iteration":667,"passed_time":6.862719466,"remaining_time":3.410812669},
{"learn":[0.02528224897],"iteration":668,"passed_time":6.877637121,"remaining_time":3.402836901},
{"learn":[0.02527103905],"iteration":669,"passed_time":6.895587684,"remaining_time":3.396334232},
{"learn":[0.02526044457],"iteration":670,"passed_time":6.911004853,"remaining_time":3.388555286},
{"learn":[0.02524069802],"iteration":671,"passed_time":6.918723956,"remaining_time":3.376996217},
{"learn":[0.0252259348],"iteration":672,"passed_time":6.92610168,"remaining_time":3.365282688},
{"learn":[0.02521535334],"iteration":673,"passed_time":6.934201117,"remaining_time":3.353931104},
{"learn":[0.02518646762],"iteration":674,"passed_time":6.944265715,"remaining_time":3.343535344},
{"learn":[0.02516070826],"iteration":675,"passed_time":6.950294883,"remaining_time":3.331206423},
{"learn":[0.02512907549],"iteration":676,"passed_time":6.959511077,"remaining_time":3.320416659},
{"learn":[0.02509220961],"iteration":677,"passed_time":6.968478294,"remaining_time":3.30951329},
{"learn":[0.02507481643],"iteration":678,"passed_time":6.981599225,"remaining_time":3.30057931},
{"learn":[0.0250577363],"iteration":679,"passed_time":6.993173322,"remaining_time":3.290905093},
{"learn":[0.02504915198],"iteration":680,"passed_time":7.001671397,"remaining_time":3.279784399},
{"learn":[0.0250153655],"iteration":681,"passed_time":7.015400053,"remaining_time":3.271110289},
{"learn":[0.02500119735],"iteration":682,"passed_time":7.022027399,"remaining_time":3.259125454},
{"learn":[0.02497661007],"iteration":683,"passed_time":7.028996718,"remaining_time":3.247314273},
{"learn":[0.02494658672],"iteration":684,"passed_time":7.03658952,"remaining_time":3.23580394},
{"learn":[0.02492682523],"iteration":685,"passed_time":7.045893159,"remaining_time":3.225088122},
{"learn":[0.02485590668],"iteration":686,"passed_time":7.056720391,"remaining_time":3.215070571},
{"learn":[0.02483033113],"iteration":687,"passed_time":7.068402519,"remaining_time":3.205438352},
{"learn":[0.02480074472],"iteration":688,"passed_time":7.077136547,"remaining_time":3.194469472},
{"learn":[0.0247741407],"iteration":689,"passed_time":7.085108229,"remaining_time":3.183164566},
{"learn":[0.02474153768],"iteration":690,"passed_time":7.100815844,"remaining_time":3.175328648},
{"learn":[0.02469854088],"iteration":691,"passed_time":7.114350595,"remaining_time":3.166502866},
{"learn":[0.02468789434],"iteration":692,"passed_time":7.123736039,"remaining_time":3.155825345},
{"learn":[0.02466959764],"iteration":693,"passed_time":7.137254252,"remaining_time":3.146973777},
{"learn":[0.02465505115],"iteration":694,"passed_time":7.145181512,"remaining_time":3.135655196},
{"learn":[0.02463088761],"iteration":695,"passed_time":7.155514514,"remaining_time":3.125397144},
{"learn":[0.02459977529],"iteration":696,"passed_time":7.16275556,"remaining_time":3.113794741},
{"learn":[0.02457517178],"iteration":697,"passed_time":7.172813314,"remaining_time":3.103423525},
{"learn":[0.02456274775],"iteration":698,"passed_time":7.178515611,"remaining_time":3.091177681},
{"learn":[0.02453811741],"iteration":699,"passed_time":7.186825512,"remaining_time":3.080068077},
{"learn":[0.02450071599],"iteration":700,"passed_time":7.192007875,"remaining_time":3.06763246},
{"learn":[0.02447869287],"iteration":701,"passed_time":7.199172348,"remaining_time":3.056058917},
{"learn":[0.02445434123],"iteration":702,"passed_time":7.208954822,"remaining_time":3.045603957},
{"learn":[0.02443371632],"iteration":703,"passed_time":7.217788306,"remaining_time":3.034751902},
{"learn":[0.0244321611],"iteration":704,"passed_time":7.228474935,"remaining_time":3.024681001},
{"learn":[0.02442412977],"iteration":705,"passed_time":7.238504056,"remaining_time":3.01433455},
{"learn":[0.02439575749],"iteration":706,"passed_time":7.252335766,"remaining_time":3.005564893},
{"learn":[0.02437581243],"iteration":707,"passed_time":7.260109284,"remaining_time":2.99428236},
{"learn":[0.02435564403],"iteration":708,"passed_time":7.26849288,"remaining_time":2.983260124},
{"learn":[0.02433651366],"iteration":709,"passed_time":7.273812872,"remaining_time":2.97099399},
{"learn":[0.02430332271],"iteration":710,"passed_time":7.281983438,"remaining_time":2.959906067},
{"learn":[0.02427359924],"iteration":711,"passed_time":7.290071084,"remaining_time":2.948792798},
{"learn":[0.02424623295],"iteration":712,"passed_time":7.296315624,"remaining_time":2.936946121},
{"learn":[0.0242250448],"iteration":713,"passed_time":7.304068671,"remaining_time":2.925719384},
{"learn":[0.02419848974],"iteration":714,"passed_time":7.314294383,"remaining_time":2.915487971},
{"learn":[0.02416124929],"iteration":715,"passed_time":7.321618138,"remaining_time":2.904105518},
{"learn":[0.02412217545],"iteration":716,"passed_time":7.332441588,"remaining_time":2.894115717},
{"learn":[0.02408863718],"iteration":717,"passed_time":7.340128945,"remaining_time":2.88289187},
{"learn":[0.02406234919],"iteration":718,"passed_time":7.346950405,"remaining_time":2.871339449},
{"learn":[0.02405153375],"iteration":719,"passed_time":7.356878015,"remaining_time":2.861008117},
{"learn":[0.02402866503],"iteration":720,"passed_time":7.368344842,"remaining_time":2.851273524},
{"learn":[0.02399809932],"iteration":721,"passed_time":7.37796375,"remaining_time":2.840822607},
{"learn":[0.02396583693],"iteration":722,"passed_time":7.388923627,"remaining_time":2.830887752},
{"learn":[0.02394025082],"iteration":723,"passed_time":7.395362544,"remaining_time":2.819226605},
{"learn":[0.02390965774],"iteration":724,"passed_time":7.402237617,"remaining_time":2.807745303},
{"learn":[0.02389655718],"iteration":725,"passed_time":7.412532699,"remaining_time":2.797567438},
{"learn":[0.02387195543],"iteration":726,"passed_time":7.424293322,"remaining_time":2.787939583},
{"learn":[0.02385516479],"iteration":727,"passed_time":7.431307782,"remaining_time":2.776532578},
{"learn":[0.02383702095],"iteration":728,"passed_time":7.438649181,"remaining_time":2.765259161},
{"learn":[0.02383559115],"iteration":729,"passed_time":7.451877754,"remaining_time":2.756173964},
{"learn":[0.02382322292],"iteration":730,"passed_time":7.463298535,"remaining_time":2.746412183},
{"learn":[0.02382103677],"iteration":731,"passed_time":7.473097109,"remaining_time":2.736051947},
{"learn":[0.02379364049],"iteration":732,"passed_time":7.483593675,"remaining_time":2.725947491},
{"learn":[0.02378786036],"iteration":733,"passed_time":7.490910225,"remaining_time":2.714689537},
{"learn":[0.02375898053],"iteration":734,"passed_time":7.499386379,"remaining_time":2.703860395},
{"learn":[0.02373688893],"iteration":735,"passed_time":7.508564312,"remaining_time":2.693289373},
{"learn":[0.02372299944],"iteration":736,"passed_time":7.517787386,"remaining_time":2.682738239},
{"learn":[0.02371912609],"iteration":737,"passed_time":7.533038546,"remaining_time":2.674330758},
{"learn":[0.02370644001],"iteration":738,"passed_time":7.540881096,"remaining_time":2.663288182},
{"learn":[0.0236783154],"iteration":739,"passed_time":7.54712767,"remaining_time":2.651693506},
{"learn":[0.02364828163],"iteration":740,"passed_time":7.554913907,"remaining_time":2.64065142},
{"learn":[0.02360059828],"iteration":741,"passed_time":7.565666785,"remaining_time":2.630649637},
{"learn":[0.02357261115],"iteration":742,"passed_time":7.570639574,"remaining_time":2.618646528},
{"learn":[0.02355856847],"iteration":743,"passed_time":7.581323571,"remaining_time":2.608627465},
{"learn":[0.02354130288],"iteration":744,"passed_time":7.589458386,"remaining_time":2.597734079},
{"learn":[0.0235398198],"iteration":745,"passed_time":7.602282979,"remaining_time":2.588444875},
{"learn":[0.02352021314],"iteration":746,"passed_time":7.615801597,"remaining_time":2.579381264},
{"learn":[0.02350274839],"iteration":747,"passed_time":7.629701077,"remaining_time":2.570434053},
{"learn":[0.02348573029],"iteration":748,"passed_time":7.638403402,"remaining_time":2.559731981},
{"learn":[0.02345432293],"iteration":749,"passed_time":7.650843771,"remaining_time":2.550281257},
{"learn":[0.02341769866],"iteration":750,"passed_time":7.662419058,"remaining_time":2.540535746},
{"learn":[0.02340553432],"iteration":751,"passed_time":7.675594973,"remaining_time":2.531313236},
{"learn":[0.02337782215],"iteration":752,"passed_time":7.69263542,"remaining_time":2.523347874},
{"learn":[0.02335789706],"iteration":753,"passed_time":7.708038139,"remaining_time":2.514824114},
{"learn":[0.02330199479],"iteration":754,"passed_time":7.717974229,"remaining_time":2.504508193},
{"learn":[0.02327993319],"iteration":755,"passed_time":7.726779708,"remaining_time":2.493828371},
{"learn":[0.02325351922],"iteration":756,"passed_time":7.737956646,"remaining_time":2.483914749},
{"learn":[0.02323316384],"iteration":757,"passed_time":7.743786588,"remaining_time":2.472290705},
{"learn":[0.0232317912],"iteration":758,"passed_time":7.750786782,"remaining_time":2.461053511},
{"learn":[0.02319766653],"iteration":759,"passed_time":7.755046896,"remaining_time":2.448962178},
{"learn":[0.02317621687],"iteration":760,"passed_time":7.761572609,"remaining_time":2.437602961},
{"learn":[0.02315845447],"iteration":761,"passed_time":7.771307638,"remaining_time":2.427258816},
{"learn":[0.02314638258],"iteration":762,"passed_time":7.778239786,"remaining_time":2.416045648},
{"learn":[0.02313409935],"iteration":763,"passed_time":7.784789597,"remaining_time":2.404725582},
{"learn":[0.02311459156],"iteration":764,"passed_time":7.788515867,"remaining_time":2.392550626},
{"learn":[0.02308074362],"iteration":765,"passed_time":7.794956653,"remaining_time":2.381226967},
{"learn":[0.02305418501],"iteration":766,"passed_time":7.80016043,"remaining_time":2.369540261},
{"learn":[0.02303574895],"iteration":767,"passed_time":7.803397346,"remaining_time":2.357276282},
{"learn":[0.02301160576],"iteration":768,"passed_time":7.809387596,"remaining_time":2.345862854},
{"learn":[0.02298055035],"iteration":769,"passed_time":7.815003417,"remaining_time":2.33435167},
{"learn":[0.02295775463],"iteration":770,"passed_time":7.821850354,"remaining_time":2.323221441},
{"learn":[0.02290826056],"iteration":771,"passed_time":7.829606463,"remaining_time":2.312370821},
{"learn":[0.02287892223],"iteration":772,"passed_time":7.835403343,"remaining_time":2.300952857},
{"learn":[0.02285157726],"iteration":773,"passed_time":7.845517201,"remaining_time":2.290809932},
{"learn":[0.02282826753],"iteration":774,"passed_time":7.853587932,"remaining_time":2.280073916},
{"learn":[0.02281803225],"iteration":775,"passed_time":7.863008963,"remaining_time":2.269734546},
{"learn":[0.02281496565],"iteration":776,"passed_time":7.874160167,"remaining_time":2.259894102},
{"learn":[0.02280531235],"iteration":777,"passed_time":7.880197261,"remaining_time":2.248590992},
{"learn":[0.02277207984],"iteration":778,"passed_time":7.888557996,"remaining_time":2.237960612},
{"learn":[0.02273442805],"iteration":779,"passed_time":7.89611305,"remaining_time":2.227108809},
{"learn":[0.02270485168],"iteration":780,"passed_time":7.901102375,"remaining_time":2.215545992},
{"learn":[0.02268553081],"iteration":781,"passed_time":7.907935669,"remaining_time":2.204514036},
{"learn":[0.02267522168],"iteration":782,"passed_time":7.913625483,"remaining_time":2.1931759},
{"learn":[0.02264778367],"iteration":783,"passed_time":7.921163115,"remaining_time":2.182361266},
{"learn":[0.02261959149],"iteration":784,"passed_time":7.927930144,"remaining_time":2.171343925},
{"learn":[0.02261017152],"iteration":785,"passed_time":7.93630054,"remaining_time":2.160773938},
{"learn":[0.0225996487],"iteration":786,"passed_time":7.942096597,"remaining_time":2.149512802},
{"learn":[0.02257626929],"iteration":787,"passed_time":7.949449783,"remaining_time":2.138684459},
{"learn":[0.02254659513],"iteration":788,"passed_time":7.957706442,"remaining_time":2.128106539},
{"learn":[0.02253296812],"iteration":789,"passed_time":7.966471922,"remaining_time":2.117669751},
{"learn":[0.02251946998],"iteration":790,"passed_time":7.972079373,"remaining_time":2.106402767},
{"learn":[0.02248917377],"iteration":791,"passed_time":7.978308554,"remaining_time":2.095313358},
{"learn":[0.02246486433],"iteration":792,"passed_time":7.984137185,"remaining_time":2.084131649},
{"learn":[0.0224408476],"iteration":793,"passed_time":7.992767693,"remaining_time":2.073690359},
{"learn":[0.02241696211],"iteration":794,"passed_time":7.997942332,"remaining_time":2.062362488},
{"learn":[0.02238588205],"iteration":795,"passed_time":8.001547006,"remaining_time":2.050647725},
{"learn":[0.0223753552],"iteration":796,"passed_time":8.0064328,"remaining_time":2.039279621},
{"learn":[0.02235790594],"iteration":797,"passed_time":8.010629224,"remaining_time":2.027753262},
{"learn":[0.02234876455],"iteration":798,"passed_time":8.01408568,"remaining_time":2.016059101},
{"learn":[0.02230441915],"iteration":799,"passed_time":8.018162033,"remaining_time":2.004540508},
{"learn":[0.02228289989],"iteration":800,"passed_time":8.02170187,"remaining_time":1.992907206},
{"learn":[0.02227337414],"iteration":801,"passed_time":8.025605108,"remaining_time":1.981383805},
{"learn":[0.02224326714],"iteration":802,"passed_time":8.02901575,"remaining_time":1.969758534},
{"learn":[0.02222072471],"iteration":803,"passed_time":8.032567919,"remaining_time":1.958188199},
{"learn":[0.0221937148],"iteration":804,"passed_tim,
{"learn":[0.02090729452],"iteration":805,"passed_time":8.135121269,"remaining_time":1.958081298},
{"learn":[0.02088976544],"iteration":806,"passed_time":8.1412875,"remaining_time":1.947048931},
{"learn":[0.02088273111],"iteration":807,"passed_time":8.15269785,"remaining_time":1.937274737},
{"learn":[0.02086500838],"iteration":808,"passed_time":8.164287924,"remaining_time":1.927538929},
{"learn":[0.02085036614],"iteration":809,"passed_time":8.175761277,"remaining_time":1.917771164},
{"learn":[0.02083824028],"iteration":810,"passed_time":8.181341295,"remaining_time":1.906625777},
{"learn":[0.02080744499],"iteration":811,"passed_time":8.188051104,"remaining_time":1.895755674},
{"learn":[0.02078902926],"iteration":812,"passed_time":8.1932096,"remaining_time":1.884538985},
{"learn":[0.02075316031],"iteration":813,"passed_time":8.20061162,"remaining_time":1.87384983},
{"learn":[0.02072966364],"iteration":814,"passed_time":8.205222838,"remaining_time":1.862535245},
{"learn":[0.02071319151],"iteration":815,"passed_time":8.209356175,"remaining_time":1.851129334},
{"learn":[0.02068648371],"iteration":816,"passed_time":8.21528237,"remaining_time":1.840142807},
{"learn":[0.02067426909],"iteration":817,"passed_time":8.219331438,"remaining_time":1.828751005},
{"learn":[0.0206454363],"iteration":818,"passed_time":8.224449843,"remaining_time":1.817613457},
{"learn":[0.02061788127],"iteration":819,"passed_time":8.231908228,"remaining_time":1.807004245},
{"learn":[0.0205968697],"iteration":820,"passed_time":8.240379637,"remaining_time":1.796623575},
{"learn":[0.02056583544],"iteration":821,"passed_time":8.247247526,"remaining_time":1.785900316},
{"learn":[0.02053939738],"iteration":822,"passed_time":8.254037476,"remaining_time":1.775169664},
{"learn":[0.0205288637],"iteration":823,"passed_time":8.26015396,"remaining_time":1.764304729},
{"learn":[0.0205076953],"iteration":824,"passed_time":8.266232901,"remaining_time":1.753443343},
{"learn":[0.02046813935],"iteration":825,"passed_time":8.270032513,"remaining_time":1.742113387},
{"learn":[0.02043741137],"iteration":826,"passed_time":8.274556073,"remaining_time":1.730953084},
{"learn":[0.02043656795],"iteration":827,"passed_time":8.280123357,"remaining_time":1.720025625},
{"learn":[0.02043593458],"iteration":828,"passed_time":8.285156129,"remaining_time":1.709000842},
{"learn":[0.0204206489],"iteration":829,"passed_time":8.289257213,"remaining_time":1.69779967},
{"learn":[0.0204061625],"iteration":830,"passed_time":8.293395759,"remaining_time":1.686623205},
{"learn":[0.02038097109],"iteration":831,"passed_time":8.297522695,"remaining_time":1.675461313},
{"learn":[0.02036834721],"iteration":832,"passed_time":8.30410653,"remaining_time":1.664808872},
{"learn":[0.02031885922],"iteration":833,"passed_time":8.309302253,"remaining_time":1.653889897},
{"learn":[0.02029547026],"iteration":834,"passed_time":8.315666962,"remaining_time":1.643215627},
{"learn":[0.02027433479],"iteration":835,"passed_time":8.321491141,"remaining_time":1.632445631},
{"learn":[0.02025979799],"iteration":836,"passed_time":8.325917688,"remaining_time":1.621415273},
{"learn":[0.02024991404],"iteration":837,"passed_time":8.33142603,"remaining_time":1.610609805},
{"learn":[0.02023901668],"iteration":838,"passed_time":8.335647675,"remaining_time":1.599570054},
{"learn":[0.02021482838],"iteration":839,"passed_time":8.340413476,"remaining_time":1.588650186},
{"learn":[0.0201908062],"iteration":840,"passed_time":8.346041482,"remaining_time":1.577907962},
{"learn":[0.0201816978],"iteration":841,"passed_time":8.351022075,"remaining_time":1.567056399},
{"learn":[0.02017015712],"iteration":842,"passed_time":8.356450477,"remaining_time":1.556302165},
{"learn":[0.02014880743],"iteration":843,"passed_time":8.360812221,"remaining_time":1.545363396},
{"learn":[0.02013676148],"iteration":844,"passed_time":8.368297235,"remaining_time":1.535013102},
{"learn":[0.0201261463],"iteration":845,"passed_time":8.373039114,"remaining_time":1.524170241},
{"learn":[0.02011318642],"iteration":846,"passed_time":8.378229922,"remaining_time":1.513422878},
{"learn":[0.0200859892],"iteration":847,"passed_time":8.384828854,"remaining_time":1.502941021},
{"learn":[0.02007127321],"iteration":848,"passed_time":8.389930667,"remaining_time":1.492202039},
{"learn":[0.0200678706],"iteration":849,"passed_time":8.396303308,"remaining_time":1.481700584},
{"learn":[0.02004238203],"iteration":850,"passed_time":8.403669796,"remaining_time":1.471382843},
{"learn":[0.02003290878],"iteration":851,"passed_time":8.40923784,"remaining_time":1.460759625},
{"learn":[0.02001834532],"iteration":852,"passed_time":8.414146222,"remaining_time":1.450034578},
{"learn":[0.02000811546],"iteration":853,"passed_time":8.419874845,"remaining_time":1.439463381},
{"learn":[0.01998563229],"iteration":854,"passed_time":8.429576148,"remaining_time":1.429577242},
{"learn":[0.01997425527],"iteration":855,"passed_time":8.434974983,"remaining_time":1.418967754},
{"learn":[0.01994846275],"iteration":856,"passed_time":8.442803461,"remaining_time":1.40877584},
{"learn":[0.01993292443],"iteration":857,"passed_time":8.448022322,"remaining_time":1.398157541},
{"learn":[0.01992960029],"iteration":858,"passed_time":8.452416279,"remaining_time":1.387416409},
{"learn":[0.01991514264],"iteration":859,"passed_time":8.457066802,"remaining_time":1.376731805},
{"learn":[0.01990390714],"iteration":860,"passed_time":8.464851734,"remaining_time":1.366567237},
{"learn":[0.01990025043],"iteration":861,"passed_time":8.472773153,"remaining_time":1.356430041},
{"learn":[0.01987575023],"iteration":862,"passed_time":8.478860796,"remaining_time":1.34600687},
{"learn":[0.01987498077],"iteration":863,"passed_time":8.483359995,"remaining_time":1.335343703},
{"learn":[0.01985475818],"iteration":864,"passed_time":8.48731885,"remaining_time":1.324610456},
{"learn":[0.01983227045],"iteration":865,"passed_time":8.49237955,"remaining_time":1.314063348},
{"learn":[0.0198215292],"iteration":866,"passed_time":8.500499032,"remaining_time":1.303998121},
{"learn":[0.01980988405],"iteration":867,"passed_time":8.505838786,"remaining_time":1.293514654},
{"learn":[0.0197973524],"iteration":868,"passed_time":8.510647834,"remaining_time":1.282963022},
{"learn":[0.01979586593],"iteration":869,"passed_time":8.515067222,"remaining_time":1.272366367},
{"learn":[0.01977144679],"iteration":870,"passed_time":8.521760814,"remaining_time":1.262120718},
{"learn":[0.01977090779],"iteration":871,"passed_time":8.527443084,"remaining_time":1.251734765},
{"learn":[0.01974744243],"iteration":872,"passed_time":8.533344696,"remaining_time":1.241391496},
{"learn":[0.01972569551],"iteration":873,"passed_time":8.539836811,"remaining_time":1.231143522},
{"learn":[0.01970577708],"iteration":874,"passed_time":8.544567933,"remaining_time":1.220652562},
{"learn":[0.01969885384],"iteration":875,"passed_time":8.55308847,"remaining_time":1.210711153},
{"learn":[0.01968629135],"iteration":876,"passed_time":8.561312573,"remaining_time":1.20073141},
{"learn":[0.01965278908],"iteration":877,"passed_time":8.569046238,"remaining_time":1.190687518},
{"learn":[0.01962712681],"iteration":878,"passed_time":8.576885503,"remaining_time":1.18066342},
{"learn":[0.01960347306],"iteration":879,"passed_time":8.58519053,"remaining_time":1.1707078},
{"learn":[0.01957627012],"iteration":880,"passed_time":8.588363679,"remaining_time":1.160062744},
{"learn":[0.01956918082],"iteration":881,"passed_time":8.594041796,"remaining_time":1.149769764},
{"learn":[0.01955181066],"iteration":882,"passed_time":8.602632225,"remaining_time":1.139873126},
{"learn":[0.0195377768],"iteration":883,"passed_time":8.607303659,"remaining_time":1.129465186},
{"learn":[0.01952054433],"iteration":884,"passed_time":8.612654343,"remaining_time":1.119158474},
{"learn":[0.01950530969],"iteration":885,"passed_time":8.61700103,"remaining_time":1.108733767},
{"learn":[0.01949883262],"iteration":886,"passed_time":8.622554792,"remaining_time":1.098476541},
{"learn":[0.01948210144],"iteration":887,"passed_time":8.626676552,"remaining_time":1.088049295},
{"learn":[0.01944416927],"iteration":888,"passed_time":8.631277532,"remaining_time":1.07769607},
{"learn":[0.01941369834],"iteration":889,"passed_time":8.635880818,"remaining_time":1.067356056},
{"learn":[0.01941254442],"iteration":890,"passed_time":8.63992217,"remaining_time":1.056960176},
{"learn":[0.019399607],"iteration":891,"passed_time":8.643758631,"remaining_time":1.046553736},
{"learn":[0.01937584515],"iteration":892,"passed_time":8.647141478,"remaining_time":1.036107657},
{"learn":[0.01936076702],"iteration":893,"passed_time":8.651723267,"remaining_time":1.025819537},
{"learn":[0.01933932005],"iteration":894,"passed_time":8.655303891,"remaining_time":1.015426713},
{"learn":[0.01932808413],"iteration":895,"passed_time":8.659778312,"remaining_time":1.00515284},
{"learn":[0.01931531533],"iteration":896,"passed_time":8.662921875,"remaining_time":0.9947390782},
{"learn":[0.01930569539],"iteration":897,"passed_time":8.66798388,"remaining_time":0.9845594163},
{"learn":[0.01928346601],"iteration":898,"passed_time":8.672569865,"remaining_time":0.97433766},
{"learn":[0.01926842445],"iteration":899,"passed_time":8.67628211,"remaining_time":0.9640313455},
{"learn":[0.01926768242],"iteration":900,"passed_time":8.681781701,"remaining_time":0.9539360582},
{"learn":[0.01925574724],"iteration":901,"passed_time":8.68634042,"remaining_time":0.9437487374},
{"learn":[0.01922236343],"iteration":902,"passed_time":8.690653995,"remaining_time":0.9335475499},
{"learn":[0.01921070367],"iteration":903,"passed_time":8.694262136,"remaining_time":0.9232844746},
{"learn":[0.01919937422],"iteration":904,"passed_time":8.698122123,"remaining_time":0.9130625433},
{"learn":[0.01919891325],"iteration":905,"passed_time":8.702829859,"remaining_time":0.9029426123},
{"learn":[0.01917769981],"iteration":906,"passed_time":8.706809693,"remaining_time":0.8927599795},
{"learn":[0.0191683728],"iteration":907,"passed_time":8.711291257,"remaining_time":0.8826418454},
{"learn":[0.01915930427],"iteration":908,"passed_time":8.715764536,"remaining_time":0.8725352836},
{"learn":[0.01914010176],"iteration":909,"passed_time":8.719690534,"remaining_time":0.8623869759},
{"learn":[0.01911026228],"iteration":910,"passed_time":8.723719675,"remaining_time":0.8522624051},
{"learn":[0.01910038532],"iteration":911,"passed_time":8.728145258,"remaining_time":0.8421894547},
{"learn":[0.01907354664],"iteration":912,"passed_time":8.732907178,"remaining_time":0.832160925},
{"learn":[0.01904412168],"iteration":913,"passed_time":8.738371324,"remaining_time":0.8222099933},
{"learn":[0.01900775246],"iteration":914,"passed_time":8.743885589,"remaining_time":0.8122735247},
{"learn":[0.01898230041],"iteration":915,"passed_time":8.749141149,"remaining_time":0.8023229875},
{"learn":[0.01897025671],"iteration":916,"passed_time":8.754163856,"remaining_time":0.792361614},
{"learn":[0.01893616685],"iteration":917,"passed_time":8.758582206,"remaining_time":0.7823570162},
{"learn":[0.01891353861],"iteration":918,"passed_time":8.765072311,"remaining_time":0.7725471786},
{"learn":[0.01890456894],"iteration":919,"passed_time":8.767997546,"remaining_time":0.7624345692},
{"learn":[0.01888655028],"iteration":920,"passed_time":8.77180494,"remaining_time":0.7524132359},
{"learn":[0.01887034948],"iteration":921,"passed_time":8.776988679,"remaining_time":0.7425218188},
{"learn":[0.01886961386],"iteration":922,"passed_time":8.780712467,"remaining_time":0.7325188081},
{"learn":[0.01885285868],"iteration":923,"passed_time":8.785763313,"remaining_time":0.7226385409},
{"learn":[0.01884234988],"iteration":924,"passed_time":8.790240961,"remaining_time":0.7127222401},
{"learn":[0.01882125088],"iteration":925,"passed_time":8.798312118,"remaining_time":0.7031048561},
{"learn":[0.01880151694],"iteration":926,"passed_time":8.801837593,"remaining_time":0.6931328417},
{"learn":[0.01877662547],"iteration":927,"passed_t,
{"learn":[0.0196928172],"iteration":927,"pass,
{"learn":[0.01875346554],"iteration":928,"passed_,
{"learn":[0.01968932855],"iteration":928,"pass,
{"learn":[0.01873797998],"iteration":929,"passed_,
{"learn":[0.01968466178],"iteration":929,"pass,
{"learn":[0.01873690387],"iteration":930,"passed_,
{"learn":[0.01967133912],"iteration":930,"passed_time":8.702435319,"remaining_time":0.6449710387},
{"learn":[0.01965951684],"iteration":931,"passed_time":8.707773652,"remaining_time":0.6353311248},
{"learn":[0.0196398461],"iteration":932,"passed_time":8.710807721,"remaining_time":0.6255349596},
{"learn":[0.01961893714],"iteration":933,"passed_time":8.717580395,"remaining_time":0.6160174583},
{"learn":[0.01960813607],"iteration":934,"passed_time":8.721165691,"remaining_time":0.6062842459},
{"learn":[0.0195968564],"iteration":935,"passed_time":8.726577682,"remaining_time":0.5966890723},
{"learn":[0.0195880252],"iteration":936,"passed_time":8.730637488,"remaining_time":0.5870119122},
{"learn":[0.01957354667],"iteration":937,"passed_time":8.738213117,"remaining_time":0.5775791186},
{"learn":[0.01955618107],"iteration":938,"passed_time":8.743532752,"remaining_time":0.5680037251},
{"learn":[0.01951988006],"iteration":939,"passed_time":8.749710994,"remaining_time":0.5584921911},
{"learn":[0.01949365613],"iteration":940,"passed_time":8.758405689,"remaining_time":0.5491455214},
{"learn":[0.01947842507],"iteration":941,"passed_time":8.76303607,"remaining_time":0.5395499916},
{"learn":[0.01946169627],"iteration":942,"passed_time":8.767456107,"remaining_time":0.5299522779},
{"learn":[0.01944559904],"iteration":943,"passed_time":8.770710012,"remaining_time":0.5202963566},
{"learn":[0.01942132404],"iteration":944,"passed_time":8.773846626,"remaining_time":0.5106471581},
{"learn":[0.01940815485],"iteration":945,"passed_time":8.776704437,"remaining_time":0.5009958135},
{"learn":[0.01939276379],"iteration":946,
{"learn":[0.01851558195],"iteration":947,"passed_time":,
{"learn":[0.01938495046],"iteration":947,
{"learn":[0.01851496583],"iteration":948,"passed_time":,
{"learn":[0.0193567863],"iteration":948,,
{"learn":[0.01849504972],"iteration":949,"passed_time",
{"learn":[0.0193312798],"iteration":949,,
{"learn":[0.01848919788],"iteration":950,"passed_time",
{"learn":[0.01932377442],"iteration":950,,
{"learn":[0.01848254867],"iteration":951,"passed_time",
{"learn":[0.01930755451],"iteration":951,,
{"learn":[0.01847337595],"iteration":952,"passed_time",
{"learn":[0.01930326148],"iteration":952,,
{"learn":[0.01844472193],"iteration":953,"passed_time,
{"learn":[0.01929056524],"iteration":953,",
{"learn":[0.01843036657],"iteration":954,"passed_time,
{"learn":[0.01925182968],"iteration":954,",
{"learn":[0.01841213956],"iteration":955,"passed_time,
{"learn":[0.01924161295],"iteration":955,,
{"learn":[0.01839705888],"iteration":956,"passed_time",
{"learn":[0.01923508619],"iteration":956,,
{"learn":[0.01838066976],"iteration":957,"passed_time",
{"learn":[0.01922020667],"iteration":957,
{"learn":[0.01836997851],"iteration":958,"passed_time",
{"learn":[0.01920866395],"iteration":958,,
{"learn":[0.01836013537],"iteration":959,"passed_time",
{"learn":[0.01919911328],"iteration":959,
{"learn":[0.01835942721],"iteration":960,"passed_time":,
{"learn":[0.0191955297],"iteration":960,,
{"learn":[0.01834696481],"iteration":961,"passed_time,
{"learn":[0.01917822411],"iteration":961,",
{"learn":[0.01833624623],"iteration":962,"passed_time,
{"learn":[0.01916541417],"iteration":962,,
{"learn":[0.01832236334],"iteration":963,"passed_time",
{"learn":[0.01915370836],"iteration":963,,
{"learn":[0.01829456403],"iteration":964,"passed_tim,
{"learn":[0.01913833459],"iteration":964,"p,
{"learn":[0.01828244649],"iteration":965,"passed_tim,
{"learn":[0.01911783954],"iteration":965,",
{"learn":[0.01825696578],"iteration":966,"passed_time,
{"learn":[0.01910822991],"iteration":966,
{"learn":[0.01824463983],"iteration":967,"passed_time":,
{"learn":[0.01908141463],"iteration":967,
{"learn":[0.01821502445],"iteration":968,"passed_time":,
{"learn":[0.01906653532],"iteration":968,
{"learn":[0.01819794634],"iteration":969,"passed_time":8.96723657,"remaining_time":0.2773372135},
{"learn":[0.01817911663],"iteration":970,"passed_time":8.970037824,"remaining_time":0.2679002028},
{"learn":[0.01817831072],"iteration":971,"passed_time":8.972131833,"remaining_time":0.2584564726},
{"learn":[0.01817777736],"iteration":972,"passed_time":8.974604674,"remaining_time":0.249038362},
{"learn":[0.01816608217],"iteration":973,"passed_time":8.977452599,"remaining_time":0.2396445252},
{"learn":[0.01815192171],"iteration":974,"passed_time":8.979991802,"remaining_time":0.2302562001},
{"learn":[0.01813034375],"iteration":975,"passed_time":8.982893218,"remaining_time":0.2208908168},
{"learn":[0.01811823256],"iteration":976,"passed_time":8.984902762,"remaining_time":0.2115176699},
{"learn":[0.01810884193],"iteration":977,"passed_time":8.987482429,"remaining_time":0.2021724064},
{"learn":[0.01810843818],"iteration":978,"passed_time":8.991111715,"remaining_time":0.1928634791},
{"learn":[0.01810756437],"iteration":979,"passed_time":8.993353204,"remaining_time":0.1835378205},
{"learn":[0.0180884347],"iteration":980,"passed_time":8.995638282,"remaining_time":0.1742274489},
{"learn":[0.0180712413],"iteration":981,"passed_time":8.997625359,"remaining_time":0.1649259231},
{"learn":[0.0180440908],"iteration":982,"passed_time":8.999585972,"remaining_time":0.1556388215},
{"learn":[0.01803176788],"iteration":983,"passed_time":9.0017488,"remaining_time":0.1463698992},
{"learn":[0.01802376646],"iteration":984,"passed_time":9.003814035,"remaining_time":0.1371139193},
{"learn":[0.01799644064],"iteration":985,"passed_time":9.005841623,"remaining_time":0.1278719906},
{"learn":[0.01797502072],"iteration":986,"passed_time":9.007882313,"remaining_time":0.1186448532},
{"learn":[0.0179478318],"iteration":987,"passed_time":9.009972712,"remaining_time":0.1094328669},
{"learn":[0.01794141401],"iteration":988,"passed_time":9.011933201,"remaining_time":0.1002338374},
{"learn":[0.01792527686],"iteration":989,"passed_time":9.013993515,"remaining_time":0.09105043955},
{"learn":[0.01790021293],"iteration":990,"passed_time":9.016013094,"remaining_time":0.08188104727},
{"learn":[0.01787931665],"iteration":991,"passed_time":9.018255668,"remaining_time":0.07272786829},
{"learn":[0.01785603241],"iteration":992,"passed_time":9.020208037,"remaining_time":0.06358656219},
{"learn":[0.01784904254],"iteration":993,"passed_time":9.022506063,"remaining_time":0.05446180722},
{"learn":[0.01782247817],"iteration":994,"passed_time":9.024541378,"remaining_time":0.04534945416},
{"learn":[0.01780798827],"iteration":995,"passed_time":9.027078318,"remaining_time":0.03625332658},
{"learn":[0.01779924869],"iteration":996,"passed_time":9.029553767,"remaining_time":0.02717017182},
{"learn":[0.01778386734],"iteration":997,"passed_time":9.03169334,"remaining_time":0.01809958585},
{"learn":[0.01776362845],"iteration":998,"passed_time":9.033941137,"remaining_time":0.009042984121},
{"learn":[0.01774071468],"iteration":999,"passed_time":9.036196092,"remaining_time":0}
]}on":999,"passed_time":8.911318578,"remaining_time":0}
]}92],"iteration":999,"passed_time":8.499521352,"remaining_time":0}
]}tion":999,"passed_time":8.037422747,"remaining_time":0}
]}